Workbook

Sheet 01_Dashboard
A1: RADAR BRASIL 2027 | VERSÃO 6.1
A3: Centro de Inteligência da Copa do Mundo Feminina FIFA Brasil 2027
A5: TOTAL DE EVENTOS 86 | D5: EVENTOS FUTUROS 27 | G5: PÚBLICO ESTIMADO 127.244 | J5: PATROCINADORES 5
A9: CIDADES MONITORADAS 14 | D9: IAC MÉDIO 32.9 | G9: INP MÉDIO 76.8 | J9: ALERTAS CRÍTICOS 0.0
A13: VISÃO EXECUTIVA
A15: Status | B15: Eventos | D15: Categoria | E15: Eventos | G15: Cidade | H15: IAC | J15: Cidade | K15: INP
A16: Planejado | B16: 27 | D16: Fan Fest | E16: =COUNTIF('02_Eventos'!F2:F495,"Fan Fest") | G16: Rio de Janeiro | H16: =IFERROR(_xludf.XLOOKUP(G16,'04_Radar_IAC'!A:A,'04_Radar_IAC'!J:J),0) | J16: Rio de Janeiro | K16: =IFERROR(_xludf.XLOOKUP(J16,'05_Radar_INP'!A:A,'05_Radar_INP'!J:J),0)
A17: Confirmado | B17: 0 | D17: Workshop | E17: =COUNTIF('02_Eventos'!F2:F495,"Workshop") | G17: São Paulo | H17: =IFERROR(_xludf.XLOOKUP(G17,'04_Radar_IAC'!A:A,'04_Radar_IAC'!J:J),0) | J17: São Paulo | K17: =IFERROR(_xludf.XLOOKUP(J17,'05_Radar_INP'!A:A,'05_Radar_INP'!J:J),0)
A18: Em execução | B18: 0 | D18: Clínica esportiva | E18: =COUNTIF('02_Eventos'!F2:F495,"Clínica esportiva") | G18: Belo Horizonte | H18: =IFERROR(_xludf.XLOOKUP(G18,'04_Radar_IAC'!A:A,'04_Radar_IAC'!J:J),0) | J18: Belo Horizonte | K18: =IFERROR(_xludf.XLOOKUP(J18,'05_Radar_INP'!A:A,'05_Radar_INP'!J:J),0)
A19: Realizado | B19: 58 | D19: Seminário | E19: =COUNTIF('02_Eventos'!F2:F495,"Seminário") | G19: Salvador | H19: =IFERROR(_xludf.XLOOKUP(G19,'04_Radar_IAC'!A:A,'04_Radar_IAC'!J:J),0) | J19: Salvador | K19: =IFERROR(_xludf.XLOOKUP(J19,'05_Radar_INP'!A:A,'05_Radar_INP'!J:J),0)
A20: Cancelado | B20: 0 | D20: Ativação patrocinador | E20: =COUNTIF('02_Eventos'!F2:F495,"Ativação patrocinador") | G20: Recife | H20: =IFERROR(_xludf.XLOOKUP(G20,'04_Radar_IAC'!A:A,'04_Radar_IAC'!J:J),0) | J20: Recife | K20: =IFERROR(_xludf.XLOOKUP(J20,'05_Radar_INP'!A:A,'05_Radar_INP'!J:J),0)
D21: Legado | E21: =COUNTIF('02_Eventos'!F2:F495,"Legado") | G21: Fortaleza | H21: =IFERROR(_xludf.XLOOKUP(G21,'04_Radar_IAC'!A:A,'04_Radar_IAC'!J:J),0) | J21: Fortaleza | K21: =IFERROR(_xludf.XLOOKUP(J21,'05_Radar_INP'!A:A,'05_Radar_INP'!J:J),0)
D22: Outro | E22: =COUNTIF('02_Eventos'!F2:F495,"Outro") | G22: Brasília | H22: =IFERROR(_xludf.XLOOKUP(G22,'04_Radar_IAC'!A:A,'04_Radar_IAC'!J:J),0) | J22: Brasília | K22: =IFERROR(_xludf.XLOOKUP(J22,'05_Radar_INP'!A:A,'05_Radar_INP'!J:J),0)
G23: Porto Alegre | H23: =IFERROR(_xludf.XLOOKUP(G23,'04_Radar_IAC'!A:A,'04_Radar_IAC'!J:J),0) | J23: Porto Alegre | K23: =IFERROR(_xludf.XLOOKUP(J23,'05_Radar_INP'!A:A,'05_Radar_INP'!J:J),0)

Sheet 02_Eventos
A1: ID | B1: Status | C1: Data | D1: UF | E1: Cidade | F1: Categoria | G1: Organizador | H1: Público Estimado | I1: Patrocinador | J1: Local | K1: Latitude | L1: Longitude | M1: Link/Fonte | N1: Observações | O1: Mês | P1: Ano | Q1: Hora | R1: HoraFim | S1: FusoHorario | T1: DataFim | U1: DataCalendario
A2: EVT-0070 | B2: Realizado | C2: 45859 | D2: MG | E2: Belo Horizonte | F2: Ativação itinerante | G2: Petrobras / Ministério da Cultura / D+ Projetos | H2: 0 | I2: Petrobras | J2: Parque Jornalista Eduardo Couri (Barragem Santa Lúcia) | K2: -19.9167 | L2: -43.9345 | M2: https://agencia.petrobras.com.br/w/regionais/caravana-do-futebol-feminino-petrobras-chega-a-belo-horizonte-com-programacao-gratuita | N2: Etapa da Caravana do Futebol Feminino Petrobras realizada de 21 a 27/07/2025, com visitação gratuita, experiências imersivas, jogos, oficinas e conteúdos educativos sobre a modalidade. O projeto itinerante foi criado para mobilizar a população e incentivar meninas em preparação para a Copa do Mundo Feminina 2027. | O2: Jul | P2: 2025
A3: EVT-0071 | B3: Realizado | C3: 45887 | D3: SP | E3: São Paulo | F3: Ativação itinerante | G3: Petrobras / Ministério da Cultura / D+ Projetos / Prefeitura de São Paulo | H3: 0 | I3: Petrobras | J3: Mercado Livre Arena Pacaembu | K3: -23.5505 | L3: -46.6333 | M3: https://prefeitura.sp.gov.br/web/cultura/w/caravana-do-futebol-feminino-chega-na-cidade-com-apoio-da-prefeitura-de-s%C3%A3o-paulo | N3: Etapa da Caravana do Futebol Feminino Petrobras realizada de 18 a 24/08/2025, com entrada gratuita. A programação reuniu oficinas, jogos, ativações tecnológicas, experiências audiovisuais e encontros ligados à modalidade, com objetivo explícito de mobilizar o público e incentivar meninas rumo à Copa Feminina 2027. | O3: Ago | P3: 2025
A4: EVT-0072 | B4: Realizado | C4: 45936 | D4: RS | E4: Porto Alegre | F4: Ativação itinerante | G4: Petrobras / Ministério da Cultura / D+ Projetos | H4: 0 | I4: Petrobras | J4: Avenida Borges de Medeiros, 2651–2729, Praia de Belas | K4: -30.0346 | L4: -51.2177 | M4: https://agencia.petrobras.com.br/w/caravana-do-futebol-feminino-petrobras-chega-em-porto-alegre-com-programa%C3%A7%C3%A3o-gratuita | N4: Etapa da Caravana do Futebol Feminino Petrobras realizada de 06 a 12/10/2025. A exposição gratuita ofereceu jogos interativos, experiências com tecnologia e inteligência artificial, conteúdos sobre atletas e ações em espaços públicos e projetos sociais, mobilizando a cidade-sede para a Copa Feminina 2027. | O4: Out | P4: 2025
A5: EVT-0073 | B5: Realizado | C5: 45975 | D5: BA | E5: Salvador | F5: Ativação itinerante | G5: Petrobras / Ministério da Cultura / D+ Projetos | H5: 0 | I5: Petrobras | J5: Parque Costa Azul | K5: -12.9777 | L5: -38.5016 | M5: https://agencia.petrobras.com.br/w/caravana-do-futebol-feminino-petrobras-chega-em-salvador-com-programa%C3%A7%C3%A3o-gratuita | N5: Etapa da Caravana do Futebol Feminino Petrobras realizada de 14 a 20/11/2025, com entrada gratuita, jogos interativos, experiências audiovisuais e ações presenciais para aproximar o público da modalidade. O circuito nacional teve vínculo expresso com a mobilização para a Copa Feminina 2027. | O5: Nov | P5: 2025
A6: EVT-0030 | B6: Realizado | C6: 46047 | D6: RJ | E6: Rio de Janeiro | F6: Lançamento oficial | G6: FIFA | H6: 0 | J6: Avenida Atlântica, Copacabana | K6: -22.9068 | L6: -43.1729 | M6: https://www.fifa.com/pt/tournaments/womens/womensworldcup/brazil-2027/articles/copa-mundo-feminina-brasil-marca-emblema-oficial | N6: Evento público realizado em 25/01/2026, em Copacabana, para iniciar a jornada rumo à Copa do Mundo Feminina 2027 e apresentar oficialmente o emblema, o slogan “Vai Ser Épico” e a identidade sonora do torneio. | O6: Jan | P6: 2026
A7: EVT-0051 | B7: Realizado | C7: 46084 | D7: RJ | E7: Rio de Janeiro | F7: Lançamento de programa | G7: Prefeitura do Rio / Secretaria Municipal de Esportes | H7: 500 | J7: Vila Olímpica Apolinho | K7: -22.9068 | L7: -43.1729 | M7: https://esportes.prefeitura.rio/noticias/prefeitura-lanca-o-projeto-rio-capital-do-futebol-feminino/ | N7: Lançamento do projeto “Rio: Capital do Futebol Feminino”, realizado em 03/03/2026 na Vila Olímpica Apolinho. A iniciativa vinculada ao legado da Copa 2027 oferece futebol a até 500 meninas de 10 a 15 anos em dez Vilas Olímpicas, com participação de pioneiras da Seleção e ações educativas contra violência e discriminação. | O7: Mar | P7: 2026
A8: EVT-0056 | B8: Realizado | C8: 46088 | D8: RS | E8: Porto Alegre | F8: Vistoria técnica | G8: FIFA / Prefeitura de Porto Alegre / Secopa 2027 | H8: 0 | J8: Estádio Beira-Rio, campos do Sesc, Vila Ventura e Ulbra | K8: -30.0346 | L8: -51.2177 | M8: https://prefeitura.poa.br/secopa2027/noticias/copa-feminina-prefeitura-acompanha-vistoria-da-fifa-em-centros-de-treinamento | N8: Vistoria realizada em 07/03/2026 pela FIFA em centros de treinamento de Porto Alegre e da Região Metropolitana. Foram avaliados o Estádio Beira-Rio e campos do Sesc, Vila Ventura e Ulbra, com análise de gramado, irrigação, gols e equipamentos para verificar a adequação às exigências de preparação das seleções na Copa Feminina 2027. | O8: Mar | P8: 2026
A9: EVT-0027 | B9: Realizado | C9: 46089 | D9: RS | E9: Porto Alegre | F9: Jogo comemorativo | G9: Prefeitura de Porto Alegre / Secopa 2027 | H9: 0 | J9: Quadra 20, Trecho 3 da Orla do Guaíba | K9: -30.0346 | L9: -51.2177 | M9: https://www.prefeitura.poa.br/secopa2027/noticias/gre-nal-feminino-pelo-dia-da-mulher-sera-no-trecho-3-da-orla-neste-domingo | N9: Gre-Nal feminino realizado em 08/03/2026, com entrada gratuita, reunindo pioneiras e ex-atletas de Grêmio e Internacional. A ação homenageou o Dia Internacional da Mulher, valorizou jogadoras e profissionais do esporte e integrou a preparação de Porto Alegre para a Copa 2027. | O9: Mar | P9: 2026
A10: EVT-0047 | B10: Realizado | C10: 46091 | D10: DF | E10: Brasília | F10: Oficina estratégica | G10: GECOPA / Ministério do Esporte / Ministério da Gestão e da Inovação | H10: 0 | J10: Local a definir | K10: -15.7939 | L10: -47.8828 | M10: https://www.gov.br/esporte/pt-br/noticias-e-conteudos/esporte/com-coordenacao-do-mesp-o-gecopa-comeca-a-tracar-primeiras-estrategias-e-desafios-para-a-copa-do-mundo-feminina-da-fifa-2027 | N10: Oficina estratégica “A Copa que Queremos”, realizada em 10/03/2026, reuniu representantes de 25 ministérios para alinhar a visão do Governo Federal para a Copa Feminina 2027. O encontro definiu diretrizes, indicadores, orientações e os primeiros passos dos planos operacionais das dez câmaras temáticas, com foco também em governança, sustentabilidade e legado social, esportivo e ambiental. A fonte não informa o local físico da oficina. | O10: Mar | P10: 2026
A11: EVT-0053 | B11: Realizado | C11: 46109 | D11: CE | E11: Fortaleza | F11: Torneio de futebol feminino | G11: Prefeitura de Fortaleza / Secretaria Municipal do Esporte e Lazer | H11: 300 | J11: Areninha do José Walter e Areninha Sargento Hermínio | K11: -3.7319 | L11: -38.5267 | M11: https://www.fortaleza.ce.gov.br/noticias/copa-feminina-guerreiras-do-sol-coloca-protagonismo-feminino-em-campo-nos-bairros-de-fortaleza | N11: Primeira Copa Feminina Guerreiras do Sol, promovida no contexto de Fortaleza como cidade-sede da Copa 2027. A fase inicial reuniu sete equipes de núcleos do projeto Atleta Cidadão em 28/03/2026, na Areninha do José Walter; a final ocorreu em 22/04/2026, na Areninha Sargento Hermínio, com cerca de 300 pessoas. | O11: Mar | P11: 2026
A12: EVT-0060 | B12: Realizado | C12: 46126 | D12: BR | E12: Local a definir | F12: Reunião estratégica | G12: Secopa27 / Ministério do Esporte / Secom / EBC / Embratur / MRE | H12: 0 | J12: Local a definir | M12: https://rncp.ebc.com.br/noticias/geral/ebc-e-esporte-iniciam-articulacao-para-copa-do-mundo-feminina-2027 | N12: Primeiro encontro para construção da estratégia de comunicação da Copa Feminina 2027, realizado em 14/04/2026. A agenda iniciou a coordenação permanente entre Secopa27, Secom, EBC, Embratur e Ministério das Relações Exteriores, com foco em legado social, igualdade de gênero, valorização do futebol feminino e promoção internacional do Brasil. A fonte não informa a cidade nem o local físico. | O12: Abr | P12: 2026
A13: EVT-0028 | B13: Realizado | C13: 46127 | D13: RS | E13: Porto Alegre | F13: Premiação | G13: Prefeitura de Porto Alegre / Secopa 2027 | H13: 0 | J13: Teatro Túlio Piva | K13: -30.0346 | L13: -51.2177 | M13: https://prefeitura.poa.br/secopa2027/noticias/premio-elas-no-campo-sera-entregue-nesta-quarta-feira-na-capital | N13: Cerimônia do Prêmio Elas no Campo realizada em 15/04/2026 para reconhecer atletas, treinadoras, profissionais, projetos sociais e pioneiras do futebol feminino. A iniciativa integrou a programação de Porto Alegre como cidade-sede e as ações de legado da Copa 2027. | O13: Abr | P13: 2026
A14: EVT-0057 | B14: Realizado | C14: 46135 | D14: RS | E14: Porto Alegre | F14: Reunião de trabalho | G14: Prefeitura de Porto Alegre / FIFA / Governo Federal | H14: 0 | J14: SmartLab do Centro Administrativo Municipal | K14: -30.0346 | L14: -51.2177 | M14: https://prefeitura.poa.br/secopa2027/noticias/copa-feminina-prefeitura-recebe-representantes-do-governo-federal-e-da-fifa | N14: Reunião de trabalho realizada em 23/04/2026 com Prefeitura de Porto Alegre, FIFA e representantes de órgãos federais e estaduais para iniciar o alinhamento da cidade-sede. Foram tratados saúde, segurança, turismo, mobilidade e comunicação; a agenda antecedeu a visita técnica ao Beira-Rio registrada separadamente no EVT-0049. | O14: Abr | P14: 2026
A15: EVT-0049 | B15: Realizado | C15: 46136 | D15: RS | E15: Porto Alegre | F15: Visita técnica | G15: Ministério do Esporte / Governo do Rio Grande do Sul / Prefeitura de Porto Alegre | H15: 0 | J15: Estádio Beira-Rio | K15: -30.0346 | L15: -51.2177 | M15: https://www.gov.br/esporte/pt-br/noticias-e-conteudos/esporte/ministerio-do-esporte-inicia-visitas-tecnicas-aos-estadios-da-copa-do-mundo-feminina-2027 | N15: Visita técnica realizada em 24/04/2026 ao Estádio Beira-Rio para a preparação da Copa Feminina 2027. Porto Alegre abriu o ciclo de vistorias do Ministério do Esporte aos estádios das oito cidades-sede. | O15: Abr | P15: 2026
A16: EVT-0066 | B16: Realizado | C16: 46140 | D16: BR | E16: Local a definir | F16: Consulta pública nacional | G16: Ministério do Esporte / Governo Federal | H16: 0 | J16: Plataforma Brasil Participativo | M16: https://www.gov.br/esporte/pt-br/noticias-e-conteudos/esporte/ministerio-do-esporte-abre-consulta-publica-para-construir-legado-da-copa-feminina-2027 | N16: Consulta pública nacional anunciada em 28/04/2026 para orientar o Plano Nacional do Legado Social e Esportivo da Copa Feminina 2027. A participação ocorreu pela plataforma Brasil Participativo, com propostas individuais e encontros autogestionados sobre visibilidade e investimento no futebol feminino, políticas para mulheres, formação, segurança, combate à violência e desenvolvimento das cidades-sede. O processo recebeu contribuições até 24/06/2026; a ação foi virtual e a fonte não informa uma cidade física. | O16: Abr | P16: 2026
A17: EVT-0037 | B17: Realizado | C17: 46141 | D17: PE | E17: Recife | F17: Reunião e visita técnica | G17: Prefeitura do Recife / FIFA | H17: 0 | J17: Arena de Pernambuco e Bairro do Recife | K17: -8.0476 | L17: -34.877 | M17: https://www2.recife.pe.gov.br/noticias/29/04/2026/recife-apresenta-planejamento-para-copa-do-mundo-feminina-da-fifa-2027 | N17: Agenda realizada em 29/04/2026 para apresentação do planejamento municipal da Copa Feminina 2027 a equipes da FIFA e instituições envolvidas. Incluiu reunião de trabalho na Arena de Pernambuco e visita técnica a pontos do Bairro do Recife, entre eles a área prevista para a FIFA Fan Fest no Cais da Alfândega. | O17: Abr | P17: 2026
A18: EVT-0050 | B18: Realizado | C18: 46147 | D18: SP | E18: São Paulo | F18: Visita técnica e reunião de legado | G18: Ministério do Esporte / Governo de São Paulo / Prefeitura de São Paulo | H18: 0 | J18: Arena Itaquera e Museu do Futebol | K18: -23.5505 | L18: -46.6333 | M18: https://www.gov.br/esporte/pt-br/noticias-e-conteudos/esporte/arena-itaquera-recebe-ministerio-do-esporte-em-preparacao-para-a-copa-do-mundo-feminina-de-2027 | N18: Agenda realizada em 05/05/2026 com visita técnica à Arena Itaquera para avaliar a infraestrutura da sede paulista e reunião no Museu do Futebol sobre ações de formação, memória e valorização da história do futebol feminino como legado da Copa 2027. | O18: Mai | P18: 2026
A19: EVT-0043 | B19: Realizado | C19: 46149 | D19: RJ | E19: Rio de Janeiro | F19: Reunião técnica | G19: Prefeitura do Rio / FIFA / Governo Federal | H19: 0 | J19: Centro de Operações e Resiliência do Rio | K19: -22.9068 | L19: -43.1729 | M19: https://prefeitura.rio/casa-civil/prefeitura-do-rio-recebe-visita-tecnica-de-delegacoes-da-fifa-e-do-governo-federal/ | N19: Reunião técnica realizada em 07/05/2026 com Prefeitura do Rio, FIFA, Secopa federal e representantes de órgãos federais e estaduais. A cidade apresentou a governança do comitê local e o planejamento operacional para receber os jogos da Copa Feminina 2027 no Maracanã. | O19: Mai | P19: 2026
A20: EVT-0033 | B20: Realizado | C20: 46150 | D20: CE | E20: Fortaleza | F20: Painel | G20: Ministério do Turismo / Prefeitura de Belo Horizonte / Belotur | H20: 0 | J20: Centro de Eventos do Ceará | K20: -3.7319 | L20: -38.5267 | M20: https://prefeitura.pbh.gov.br/noticias/belo-horizonte-tera-destaque-na-programacao-do-salao-nacional-do-turismo | N20: Mesa “Preparativos para a Copa do Mundo de Futebol Feminino 2027”, realizada em 08/05/2026 durante o Salão Nacional do Turismo. Belo Horizonte apresentou ativos, projetos e estratégias de turismo vinculados à preparação da cidade-sede para o Mundial. | O20: Mai | P20: 2026
A21: EVT-0034 | B21: Realizado | C21: 46153 | D21: MG | E21: Belo Horizonte | F21: Reunião e visita técnica | G21: Prefeitura de Belo Horizonte / FIFA / Ministério do Esporte / Governo de Minas Gerais | H21: 0 | J21: Mineirão | K21: -19.9167 | L21: -43.9345 | M21: https://prefeitura.pbh.gov.br/noticias/pbh-recebe-comitiva-da-fifa-e-ministerio-dos-esportes-como-preparacao-para-copa-feminina | N21: Primeira reunião intersetorial de preparação de Belo Horizonte para a Copa Feminina 2027, realizada em 11/05/2026 com representantes municipais, estaduais, federais e da FIFA. A agenda incluiu visita técnica ao Mineirão e alinhamento das entregas operacionais da cidade-sede. | O21: Mai | P21: 2026
A22: EVT-0026 | B22: Realizado | C22: 46155 | D22: RS | E22: Porto Alegre | F22: Consulta pública | G22: Prefeitura de Porto Alegre / Secopa 2027 | H22: 0 | J22: Espaço SmartLab do Centro Administrativo Municipal | K22: -30.0346 | L22: -51.2177 | M22: https://prefeitura.poa.br/secopa2027/noticias/consulta-publica-debate-o-legado-da-copa-do-mundo-de-futebol-feminino-em-porto | N22: Consulta pública realizada em 13/05/2026 para debater o legado da Copa do Mundo Feminina 2027 em Porto Alegre. Foram discutidas propostas nas áreas de esporte, desenvolvimento social e econômico, planejamento urbano e políticas públicas para as mulheres; três propostas selecionadas foram encaminhadas ao governo federal. | O22: Mai | P22: 2026
A23: EVT-0045 | B23: Realizado | C23: 46155 | D23: BA | E23: Salvador | F23: Reunião técnica | G23: Prefeitura de Salvador / FIFA / Governo Federal | H23: 0 | J23: Arena Fonte Nova | K23: -12.9777 | L23: -38.5016 | M23: https://salvador.ba.gov.br/prefeitura-apresenta-estrategias-para-copa-do-mundo-feminina-em-salvador-durante-encontro-com-a-fifa/ | N23: Reunião realizada em 13/05/2026 para alinhar os preparativos de Salvador para a Copa Feminina 2027. A Prefeitura apresentou à FIFA e ao governo federal os planos de mobilidade, serviços públicos, comunicação, segurança, turismo, sustentabilidade, direitos humanos e organização do comércio informal no entorno da Arena Fonte Nova. | O23: Mai | P23: 2026
A24: EVT-0058 | B24: Realizado | C24: 46155 | D24: CE | E24: Fortaleza | F24: Reunião de planejamento | G24: Prefeitura de Fortaleza / FIFA | H24: 0 | J24: Paço Municipal | K24: -3.7319 | L24: -38.5267 | M24: https://www.fortaleza.ce.gov.br/noticias/prefeitura-de-fortaleza-recebe-representantes-da-fifa-para-planejamento-da-copa-do-mundo-feminina-de-2027 | N24: Reunião de planejamento realizada em 13/05/2026 entre a Prefeitura de Fortaleza e representantes da FIFA. O encontro tratou da organização, logística, turismo, economia, legado social e equidade de gênero para a Copa Feminina 2027, além de preparar a visita técnica ampliada da semana seguinte. | O24: Mai | P24: 2026
A25: EVT-0032 | B25: Realizado | C25: 46160 | D25: CE | E25: Fortaleza | F25: Visita técnica | G25: Ministério do Esporte / Governo do Ceará / MPCE | H25: 0 | J25: Arena Castelão | K25: -3.7319 | L25: -38.5267 | M25: https://mpce.mp.br/mp-do-ceara-acompanha-visita-tecnica-de-comitiva-do-ministerio-do-esporte-a-arena-castelao-em-preparacao-para-os-jogos-da-copa-do-mundo-feminina-2027/ | N25: Visita técnica realizada em 18/05/2026 para alinhar a preparação da Arena Castelão para a Copa Feminina 2027, com participação do Ministério do Esporte, Governo do Ceará e Ministério Público. A agenda abordou integração institucional, segurança, cultura de paz, inclusão e legado do futebol feminino. | O25: Mai | P25: 2026
A26: EVT-0059 | B26: Realizado | C26: 46160 | D26: CE | E26: Fortaleza | F26: Reunião e visita técnica | G26: Prefeitura de Fortaleza / Governo do Ceará / Governo Federal / FIFA | H26: 0 | J26: Paço Municipal, Arena Castelão e Aterro da Praia de Iracema | K26: -3.7319 | L26: -38.5267 | M26: https://www.fortaleza.ce.gov.br/noticias/fortaleza-recebe-comitivas-da-fifa-governo-federal-e-governo-do-estado-para-alinhamento-da-copa-do-mundo-feminina-de-2027 | N26: Agenda realizada em 18/05/2026 para alinhar a preparação de Fortaleza como cidade-sede da Copa Feminina 2027. Após reunião no Paço Municipal, a comitiva vistoriou a Arena Castelão e visitou o Aterro da Praia de Iracema, área prevista para receber a FIFA Fan Fest. | O26: Mai | P26: 2026
A27: EVT-0048 | B27: Realizado | C27: 46162 | D27: DF | E27: Brasília | F27: Reunião e visita técnica | G27: Ministério do Esporte / FIFA / Governo do Distrito Federal | H27: 0 | J27: Ministério do Esporte e Estádio Nacional Mané Garrincha | K27: -15.7939 | L27: -47.8828 | M27: https://www.gov.br/esporte/pt-br/noticias-e-conteudos/esporte/ultima-cidade-a-receber-visita-tecnica-brasilia-avanca-no-planejamento-para-a-copa-do-mundo-de-futebol-feminino-2027 | N27: Agenda realizada em 20/05/2026 para alinhar a preparação de Brasília para a Copa Feminina 2027. A reunião institucional e a visita técnica ao Estádio Nacional Mané Garrincha encerraram o ciclo de vistorias do Ministério do Esporte às oito cidades-sede, com avaliação de estrutura, operação e planejamento local. | O27: Mai | P27: 2026
A28: EVT-0038 | B28: Realizado | C28: 46167 | D28: SP | E28: São Paulo | F28: Encontro e painéis | G28: Prefeitura de São Paulo / Secretaria Municipal de Turismo | H28: 0 | J28: Praça das Artes | K28: -23.5505 | L28: -46.6333 | M28: https://prefeitura.sp.gov.br/web/turismo/w/prefeitura-de-s%C3%A3o-paulo-promove-encontro-sobre-futebol-feminino-e-copa-do-mundo | N28: Evento Mulheres em Campo, realizado em 25/05/2026, com mesas sobre transformação social, impactos da Copa Feminina 2027 no turismo e nos eventos, além de infraestrutura, mobilidade, inclusão e legado para São Paulo. | O28: Mai | P28: 2026
A29: EVT-0075 | B29: Realizado | C29: 46175 | D29: BA | E29: Local a definir | F29: Planejamento de mobilidade | G29: Governo da Bahia / Sedur | H29: 0 | J29: Local a definir | M29: https://www.ba.gov.br/sedur/noticias/2026-06/12398/sedur-participa-do-planejamento-da-copa-do-mundo-feminina-fifa-2027-e | N29: Reunião de alinhamento entre secretarias estaduais realizada em 02/06/2026 para definir responsabilidades e estratégias de mobilidade da Copa Feminina 2027 na Bahia, incluindo transporte até a Arena Fonte Nova, operações especiais e estruturação das FIFA Fan Fests. A fonte não informa a cidade nem o local físico do encontro. | O29: Jun | P29: 2026
A30: EVT-0078 | B30: Realizado | C30: 46176 | D30: PB | E30: João Pessoa | F30: Painel | G30: Ministério do Turismo / ONU Turismo | H30: 0 | J30: Centro de Convenções de João Pessoa | K30: -7.115 | L30: -34.8641 | M30: https://brasil61.com/n/copa-feminina-de-2027-e-vista-como-oportunidade-para-ampliar-direitos-e-abrir-espacos-para-mulheres-mtur260027 | N30: Painel realizado no Fórum Internacional de Turismo para Mulheres em 03/06/2026. Representantes do governo e de organismos internacionais debateram como a Copa Feminina 2027 pode ampliar direitos e deixar legados em turismo, segurança, mobilidade, autonomia econômica e liderança feminina. | O30: Jun | P30: 2026
A31: EVT-0079 | B31: Realizado | C31: 46182 | D31: CE | E31: Fortaleza | F31: Amistoso da Seleção | G31: CBF / Seleção Brasileira Feminina | H31: 55744 | J31: Arena Castelão | K31: -3.7319 | L31: -38.5267 | M31: https://www.fortaleza.ce.gov.br/noticias/fortaleza-recebe-amistoso-entre-brasil-e-estados-unidos-e-registra-maior-publico-do-futebol-feminino-no-nordeste | N31: Amistoso entre Brasil e Estados Unidos, com vitória norte-americana por 1 a 0. A fonte oficial relaciona explicitamente a partida ao início da preparação de Fortaleza para a Copa Feminina 2027 e aos testes de operação, mobilidade e recepção de público no Castelão. O público de 55.744 pessoas foi recorde do futebol feminino no Nordeste. | O31: Jun | P31: 2026
A32: EVT-0061 | B32: Realizado | C32: 46183 | D32: BR | E32: Local a definir | F32: Reunião estratégica | G32: Ministério do Esporte / Secom PR | H32: 0 | J32: Local a definir | M32: https://www.gov.br/esporte/pt-br/noticias-e-conteudos/esporte/ministerio-do-esporte-e-secom-pr-alinham-estrategias-de-comunicacao-para-a-copa-feminina-2027 | N32: Reunião estratégica realizada em 10/06/2026 entre o Ministério do Esporte e a Secom PR para alinhar ações integradas de comunicação e promoção da Copa Feminina 2027 no Brasil e no exterior, incluindo o fortalecimento da Marca Brasil. A fonte não informa a cidade nem o local físico. | O32: Jun | P32: 2026
A33: EVT-0067 | B33: Realizado | C33: 46185 | D33: PE | E33: Recife | F33: Ativação cultural e esportiva | G33: Prefeitura do Recife / Recentro / Paço do Frevo | H33: 0 | J33: Rua Barão Rodrigues Mendes — Rua do Frevo | K33: -8.0476 | L33: -34.877 | M33: https://www2.recife.pe.gov.br/noticias/10/06/2026/recentro-promove-acao-na-rua-do-frevo-unindo-copa-do-mundo-e-o-periodo-junino | N33: Ação “Rua do Frevo: onde o futebol encontra o forró”, realizada em 12/06/2026, das 11h às 17h, no Bairro do Recife. A programação reuniu gramadão de futebol, feira temática, troca de figurinhas e apresentações culturais. Embora também integrada ao clima da Copa masculina de 2026, a Prefeitura registrou referência expressa à Copa Mundial feminina e ao papel do Recife como cidade-sede em 2027. | O33: Jun | P33: 2026
A34: EVT-0029 | B34: Realizado | C34: 46197 | D34: RS | E34: Porto Alegre | F34: Ativação urbana | G34: Prefeitura de Porto Alegre / Secopa 2027 | H34: 0 | J34: Diversos espaços públicos, museus de Grêmio e Internacional e escolas municipais | K34: -30.0346 | L34: -51.2177 | M34: https://www.prefeitura.poa.br/secopa2027/noticias/porto-alegre-entra-na-contagem-regressiva-de-um-ano-para-copa-do-mundo-feminina | N34: Ativação de 24/06/2026 para marcar um ano até a Copa Feminina 2027, com iluminação de prédios e espaços públicos, visitas gratuitas aos museus de Grêmio e Internacional e ações educativas sobre a história do futebol feminino em escolas municipais. | O34: Jun | P34: 2026
A35: EVT-0031 | B35: Realizado | C35: 46197 | D35: RJ | E35: Rio de Janeiro | F35: Ativação urbana | G35: FIFA / Santuário Cristo Redentor | H35: 0 | J35: Cristo Redentor | K35: -22.9068 | L35: -43.1729 | M35: https://blog.paineirascorcovado.com.br/2026/06/25/copa-do-mundo-feminina-2027-cristo-redentor/ | N35: Ativação realizada na noite de 24/06/2026 para marcar um ano até a abertura da Copa Feminina 2027, com iluminação do Cristo Redentor em verde e amarelo e projeções temáticas sobre o torneio. | O35: Jun | P35: 2026
A36: EVT-0035 | B36: Realizado | C36: 46197 | D36: BA | E36: Salvador | F36: Ativação urbana | G36: Prefeitura de Salvador | H36: 0 | J36: Monumento à Cidade do Salvador, Arcos da Montanha, Bambuzal do Aeroporto, estações do BRT, Casa do Olodum e sede da Prefeitura | K36: -12.9777 | L36: -38.5016 | M36: https://salvador.ba.gov.br/salvador-celebra-marco-de-um-ano-para-a-copa-do-mundo-feminina-com-iluminacao-especial-em-monumentos-da-cidade/ | N36: Ativação realizada em 24/06/2026 para marcar um ano até a Copa Feminina 2027, com iluminação verde, amarela e azul em monumentos, equipamentos públicos, estações do BRT, Casa do Olodum e sede da Prefeitura. | O36: Jun | P36: 2026
A37: EVT-0040 | B37: Realizado | C37: 46197 | D37: CE | E37: Fortaleza | F37: Ativação urbana | G37: Prefeitura de Fortaleza | H37: 0 | J37: Paço Municipal, Ponte dos Ingleses e Arena Castelão | K37: -3.7319 | L37: -38.5267 | M37: https://www.fortaleza.ce.gov.br/noticias/fortaleza-inicia-contagem-regressiva-de-um-ano-para-a-copa-do-mundo-feminina-da-fifa-brasil-2027 | N37: Ativação realizada em 24/06/2026 para marcar um ano até a Copa Feminina 2027, com iluminação do Paço Municipal, da Ponte dos Ingleses e da Arena Castelão nas cores do Brasil. A ação integrou a mobilização local e a promoção do futebol feminino. | O37: Jun | P37: 2026
A38: EVT-0041 | B38: Realizado | C38: 46197 | D38: PE | E38: Recife | F38: Ativação urbana | G38: Prefeitura do Recife | H38: 0 | J38: Boulevard da Rio Branco, pontes, monumentos e polos do São João | K38: -8.0476 | L38: -34.877 | M38: https://www2.recife.pe.gov.br/noticias/23/06/2026/recife-comeca-contagem-regressiva-para-copa-do-mundo-feminina-da-fifatm | N38: Ação realizada em 24/06/2026 para marcar um ano até a Copa Feminina 2027. Incluiu participação da personagem Méry Cristina no arraial do Boulevard da Rio Branco, iluminação verde e amarela de pontes e monumentos e mensagens sobre o Mundial nos polos do São João. | O38: Jun | P38: 2026
A39: EVT-0042 | B39: Realizado | C39: 46197 | D39: DF | E39: Brasília | F39: Ativação educativa | G39: FIFA / Governo Federal / Governo do Distrito Federal | H39: 700 | J39: Estádio Nacional Mané Garrincha, Parque da Cidade e Rodoviária do Plano Piloto | K39: -15.7939 | L39: -47.8828 | M39: https://agenciabrasil.ebc.com.br/esportes/noticia/2026-06/brasilia-inicia-contagem-regressiva-de-1-ano-da-copa-do-mundo-feminina | N39: Ativação realizada em 24/06/2026 para marcar um ano até a Copa Feminina 2027. Mais de 700 estudantes dos centros olímpicos do DF visitaram o Mané Garrincha, participaram de pinturas coletivas no Parque da Cidade e de atividades de futebol na Rodoviária do Plano Piloto. | O39: Jun | P39: 2026
A40: EVT-0052 | B40: Realizado | C40: 46197 | D40: RJ | E40: Rio de Janeiro | F40: Ativação pública | G40: Prefeitura do Rio / FIFA | H40: 0 | J40: Fan Fest de Copacabana | K40: -22.9068 | L40: -43.1729 | M40: https://prefeitura.rio/cidade/pioneiras-da-selecao-feminina-de-futebol-promovem-o-mundial-com-acao-em-copacabana/ | N40: Ativação realizada em 24/06/2026 para marcar um ano até a Copa Feminina 2027. Pioneiras da Seleção interagiram com o público na Fan Fest de Copacabana, participaram de altinha, fotos e divulgação do Mundial, junto a meninas de projetos esportivos municipais. | O40: Jun | P40: 2026
A41: EVT-0054 | B41: Realizado | C41: 46199 | D41: EUA | E41: Miami | F41: Missão técnica internacional | G41: Prefeitura de Porto Alegre / Secopa 2027 | H41: 0 | J41: Miami Stadium e Goal Connect Miami 2026 | M41: https://www.prefeitura.poa.br/secopa2027/noticias/concluida-missao-tecnica-aos-estados-unidos-para-preparacao-da-copa-feminina | N41: Missão técnica concluída em 26/06/2026 durante a Copa do Mundo FIFA 2026, como parte da preparação de Porto Alegre para a Copa Feminina 2027. A agenda acompanhou operação, logística, segurança, infraestrutura, experiência do público e regras de eventos oficiais, incluiu visita ao Miami Stadium e participação no Goal Connect Miami 2026. | O41: Jun | P41: 2026
A42: EVT-0080 | B42: Realizado | C42: 46199 | D42: SP | E42: São Paulo | F42: Reunião institucional | G42: Prefeitura de São Paulo / Comissão da Copa 2027 | H42: 0 | J42: Online | K42: -23.5505 | L42: -46.6333 | M42: https://prefeitura.sp.gov.br/web/turismo/l/48770028 | N42: Reunião online realizada em 26/06/2026, às 14h30, com integrantes da Comissão da Copa do Mundo Feminina FIFA 2027. A pauta oficial foi a orientação sobre o projeto de lei relacionado ao torneio. | O42: Jun | P42: 2026
A43: EVT-0065 | B43: Realizado | C43: 46205 | D43: BR | E43: Local a definir | F43: Reunião de legado | G43: Ministério do Esporte / Câmara Temática do Legado Social e Esportivo | H43: 0 | J43: Local a definir | M43: https://www.gov.br/esporte/pt-br/noticias-e-conteudos/ministerio-do-esporte-articula-plano-de-legado-para-a-copa-do-mundo-feminina-com-foco-em-metas-para-setembro | N43: Reunião realizada em 02/07/2026 para consolidar ações interministeriais do Plano de Legado da Copa Feminina 2027. Foram apresentados resultados preliminares da consulta pública e atualizadas iniciativas de futebol feminino indígena, saúde, sustentabilidade, educação, comunicação e proteção às mulheres. A fonte oficial não informa a cidade nem o local físico. | O43: Jul | P43: 2026
A44: EVT-0046 | B44: Realizado | C44: 46211 | D44: BA | E44: Salvador | F44: Reunião de governança | G44: Prefeitura de Salvador / Grupo de Trabalho da Copa | H44: 0 | J44: Local a definir | K44: -12.9777 | L44: -38.5016 | M44: https://agenciadenoticias.salvador.ba.gov.br/index.php/pt-br/releases-2/geral/30922-governanca-integrada-marca-reuniao-da-prefeitura-para-planejamento-da-copa-do-mundo-feminina-2027 | N44: Reunião realizada em 08/07/2026 com pontos focais de 37 órgãos municipais para fortalecer a governança integrada e alinhar ações de mobilidade, segurança, turismo, cultura, infraestrutura, comunicação, assistência social, equidade de gênero e políticas para as mulheres. A fonte não informa o local físico do encontro. | O44: Jul | P44: 2026
A45: EVT-0044 | B45: Realizado | C45: 46219 | D45: EUA | E45: Nova York | F45: Promoção internacional | G45: Prefeitura de Belo Horizonte / Belotur / Embratur / Confut | H45: 0 | J45: Local a definir | M45: https://prefeitura.pbh.gov.br/noticias/pbh-participa-de-encontro-estrategico-sobre-copa-do-mundo-feminina-de-2027 | N45: Participação da delegação de Belo Horizonte no Confut USA 2026, realizado em 16 e 17/07/2026. Em painel sobre os destinos brasileiros da Copa Feminina 2027, a Belotur apresentou a infraestrutura turística, logística e operacional da cidade-sede. A fonte não informa o local físico do evento. | O45: Jul | P45: 2026
A46: EVT-0068 | B46: Realizado | C46: 46230 | D46: BR | E46: Local a definir | F46: Lançamento de programa | G46: FIFA | H46: 0 | J46: Plataforma FIFA Volunteers | M46: https://www.gov.br/esporte/pt-br/noticias/quer-viver-a-copa-do-mundo-feminina-2027-de-perto-fifa-abre-cadastro-de-interesse-para-voluntarios | N46: Abertura, em 27/07/2026, do cadastro de manifestação de interesse para o programa de voluntariado da Copa do Mundo Feminina FIFA Brasil 2027. A FIFA prevê selecionar cerca de 6 mil pessoas para atuar na organização do torneio nas oito cidades-sede; as inscrições para o processo seletivo foram anunciadas para setembro de 2026. A etapa registrada é online e não possui cidade física. | O46: Jul | P46: 2026
A47: EVT-0076 | B47: Realizado | C47: 46232 | D47: CE | E47: Fortaleza | F47: Segurança e prevenção | G47: MPCE / FIFA | H47: 0 | J47: Local a definir | K47: -3.7319 | L47: -38.5267 | M47: https://mpce.mp.br/mp-do-ceara-e-representante-da-fifa-se-reunem-para-alinhar-parceria-para-a-copa-do-mundo-feminina-de-2027/ | N47: Reunião entre o Ministério Público do Ceará e a FIFA em 29/07/2026 para alinhar prevenção e combate à violência, segurança, emergências médicas e capacitação dos profissionais da Copa Feminina 2027. O protocolo “Não é Não” será aplicado nos jogos da Arena Castelão para prevenir constrangimentos e violência contra a mulher. A fonte não informa o local físico do encontro. | O47: Jul | P47: 2026
A48: EVT-0039 | B48: Realizado | C48: 46235 | D48: SP | E48: São Paulo | F48: Encontro inclusivo | G48: Prefeitura de São Paulo / Secretaria Municipal da Pessoa com Deficiência | H48: 0 | J48: Casa Mãe Paulistana para Mães e Cuidadores de Pessoas com Deficiência | K48: -23.5505 | L48: -46.6333 | M48: https://prefeitura.sp.gov.br/web/pessoa_com_deficiencia/w/copa-do-mundo-2026-prefeitura-de-s%C3%A3o-paulo-promove-a%C3%A7%C3%B5es-inclusivas-para-pessoas-com-defici%C3%AAncia-e-seus-familiares | N48: Edição especial de aquecimento para a Copa Feminina 2027 prevista para agosto de 2026, com bate-papo da jogadora Tamires para mães, cuidadoras e familiares de pessoas com deficiência. A fonte confirma apenas o mês; o dia 01 é usado no campo técnico para ordenação e o dia exato está a definir. | O48: Ago | P48: 2026
A49: EVT-0063 | B49: Realizado | C49: 46237 | D49: SP | E49: São Paulo | F49: Fórum | G49: Fórum Sustentabilidade em Campo | H49: 0 | J49: Museu do Futebol | K49: -23.5505 | L49: -46.6333 | M49: https://www.sympla.com.br/evento/forum-sustentabilidade-em-campo/3498582 | N49: Terceira edição do Fórum Sustentabilidade em Campo, realizada em 03/08/2026, das 8h às 22h, no Museu do Futebol. A programação reuniu lideranças do esporte, sustentabilidade e negócios e incluiu painel sobre oportunidades de investimento, turismo, desenvolvimento e legado da Copa do Mundo Feminina 2027, além de debates sobre esporte feminino, governança, impacto social e grandes eventos. | O49: Ago | P49: 2026
A50: EVT-0013 | B50: Realizado | C50: 46238 | D50: SP | E50: São Paulo | F50: Seminário | G50: Grupo Mulheres do Brasil / parceiros | H50: 0 | J50: Expo Center Norte | K50: -23.5148 | L50: -46.619 | M50: https://www.oliberal.com/esportes/nao-da-para-falar-em-paixao-nacional-so-valorizando-o-masculino-diz-secretaria-da-copa-1.1153852 | N50: Summit Mulheres nas Profissões (4–5/08): painel sobre a Copa do Mundo Feminina FIFA 2027, legado e valorização do futebol feminino. | O50: Ago | P50: 2026
A51: EVT-0036 | B51: Realizado | C51: 46238 | D51: BA | E51: Salvador | F51: Reunião de legado | G51: Prefeitura de Salvador / Grupo de Trabalho da Copa | H51: 0 | J51: Local a definir | K51: -12.9777 | L51: -38.5016 | M51: https://secult.salvador.ba.gov.br/prefeitura-se-reune-com-clubes-federacao-atletas-e-entidades-para-debater-legado-social-da-copa-do-mundo-feminina-da-fifa-2027/ | N51: Reunião realizada em 04/08/2026 com Prefeitura, Federação Bahiana de Futebol, Arena Fonte Nova, clubes e profissionais do esporte para debater inclusão, categorias de base, protagonismo feminino e o legado social da Copa 2027. A fonte não informa o local físico do encontro. | O51: Ago | P51: 2026
A52: EVT-0069 | B52: Realizado | C52: 46238 | D52: RJ | E52: Rio de Janeiro | F52: Painel | G52: Rio Innovation Week / FIFA | H52: 0 | J52: Rio Innovation Week | K52: -22.9068 | L52: -43.1729 | M52: https://ge.globo.com/futebol/futebol-internacional/noticia/2026/08/04/diretor-da-copa-2027-revela-que-730-mil-pessoas-ja-mostraram-interesse-em-comprar-ingressos-a-gente-vai-encher-estadio.ghtml | N52: Painel “A Copa do Mundo de 2027 já começou”, realizado em 04/08/2026 durante a Rio Innovation Week. O diretor de operações da Copa, Thiago Jannuzzi, apresentou dados de interesse em ingressos, capacidade dos estádios e metas de público, audiência e legado social e cultural do Mundial. A fonte confirma a cidade e o evento, mas não informa o espaço físico específico do painel. | O52: Ago | P52: 2026
A53: EVT-0024 | B53: Realizado | C53: 46241 | D53: RJ | E53: Rio de Janeiro | F53: Mostra cultural | G53: CINEfoot | H53: 0 | J53: CCJF e Estação Claro Rio | K53: -22.9068 | L53: -43.1729 | M53: https://cinefoot.org/mostra-geraldinos-arquibaldos-2026/ | N53: Mostra “Rumo à Copa do Mundo Feminina 2027” no CINEfoot 16, com sessões em 07/08 no Centro Cultural Justiça Federal e em 09/08 no CCJF e na Estação Claro Rio, incluindo filmes sobre pioneiras do futebol feminino brasileiro. | O53: Ago | P53: 2026
A54: EVT-0014 | B54: Realizado | C54: 46243 | D54: SP | E54: São Paulo | F54: Ativação patrocinador | G54: FIFA / SP2B | H54: 70000 | I54: Coca-Cola; Visa; Adidas; Hyundai | J54: Parque Ibirapuera | K54: -23.5874 | L54: -46.6576 | M54: https://economia.uol.com.br/noticias/redacao/2026/08/14/copa-do-mundo-feminina-alcanca-750-mil-interessados-em-ingressos.ghtm | N54: SP2B ocorreu de 9–16/08. A FIFA promoveu summit/encontro com marcas e executivos sobre ativações e oportunidades comerciais da Copa 2027; data específica do painel não foi publicada na fonte consultada. | O54: Ago | P54: 2026
A55: EVT-0081 | B55: Realizado | C55: 46245 | D55: DF | E55: Brasília | F55: Painel / Legado | G55: Elas em Ação | H55: 0 | J55: Teatro Nacional Cláudio Santoro | K55: -15.7939 | L55: -47.8828 | M55: https://elasemacao.com/ | N55: O encontro nacional Elas em Ação — Mulheres que Transformam o Futuro incluiu, em 12/08/2026, o painel “Esporte como Arena de Poder”, dedicado ao esporte como ferramenta de transformação social e econômica e ao legado da Copa Feminina 2027. Participaram Juliana Picoli Agatte, Ruskaya Zanini e Fabíola Constâncio. | O55: Ago | P55: 2026
A56: EVT-0025 | B56: Realizado | C56: 46248 | D56: RS | E56: Porto Alegre | F56: Seminário | G56: Prefeitura de Porto Alegre / Sistema Confef-Crefs | H56: 0 | J56: Sede da FGF e Esefid/UFRGS | K56: -30.0346 | L56: -51.2177 | M56: https://prefeitura.poa.br/secopa2027/noticias/seminario-mulheres-em-campo-ocorre-nesta-sexta-feira | N56: Seminário As Mulheres em Campo, realizado em 14/08/2026, com debates sobre políticas públicas, formação, trajetórias profissionais e desenvolvimento do futebol feminino, além de oficinas e apresentação de Carta-Compromisso Local para o legado da Copa 2027. | O56: Ago | P56: 2026
A57: EVT-0015 | B57: Realizado | C57: 46251 | D57: PE | E57: Recife | F57: Workshop | G57: FIFA / Federação Pernambucana de Futebol | H57: 0 | J57: Sede da FPF | K57: -8.0476 | L57: -34.877 | M57: https://tribunaonline.com.br/pernambuco/esporte/fpf-recebe-comitiva-da-fifa-para-alinhar-preparativos-da-copa-do-mundo-feminina-328649 | N57: Comitiva da FIFA reuniu-se com a FPF para alinhar preparação, integração institucional e operação da Copa 2027 em Pernambuco. | O57: Ago | P57: 2026
A58: EVT-0016 | B58: Realizado | C58: 46254 | D58: SP | E58: São Paulo | F58: Sorteio Oficial | G58: FIFA | H58: 0 | J58: Sede da FIFA, Zurique / transmissão online | K58: -23.5505 | L58: -46.6333 | M58: https://ge.globo.com/futebol/copa-do-mundo-feminina/noticia/2026/08/14/copa-do-mundo-2027-calendario-sera-revelado-dia-20-de-agosto.ghtml | N58: Evento em 20/08, às 9h de Brasília: divulgação do calendário e distribuição de jogos por sede, cidades dos jogos do Brasil e sorteio da fase preliminar da repescagem. | O58: Ago | P58: 2026
A59: EVT-0021 | B59: Realizado | C59: 46257 | D59: SP | E59: São Paulo | F59: Summit | G59: Instituto Futuro em Jogo | H59: 0 | J59: Museu do Futebol | K59: -23.5477 | L59: -46.6657 | M59: https://www.sympla.com.br/evento/elas-jogam-summit-sao-paulo-e-o-legado-da-copa-de-2027-23-08-domingo/3508796 | N59: Elas Jogam Summit — São Paulo e o Legado da Copa 2027. Evento presencial em 23/08/2026, das 8h30 às 19h, no Museu do Futebol. | O59: Ago | P59: 2026
A60: EVT-0023 | B60: Planejado | C60: 46258 | D60: RJ | E60: Rio de Janeiro | F60: Workshop | G60: FIFA / CBF | H60: 0 | J60: A definir | K60: -22.9068 | L60: -43.1729 | M60: https://prefeitura.poa.br/secopa2027/noticias/porto-alegre-apresenta-preparacao-para-copa-feminina-2027-em-workshop-da-fifa | N60: II Workshop de Cidades-Sede e Estádios da Copa do Mundo Feminina FIFA 2027, realizado de 24 a 26/08/2026 no Rio de Janeiro, reunindo representantes das oito cidades-sede, governos, FIFA e CBF. | O60: Ago | P60: 2026
A61: EVT-0064 | B61: Planejado | C61: 46264 | D61: BA | E61: Salvador | F61: Torneio de futebol feminino | G61: Prefeitura de Salvador / Sempre / Federação Bahiana de Futebol | H61: 0 | J61: Local a definir | K61: -12.9777 | L61: -38.5016 | M61: https://comunicacao.salvador.ba.gov.br/prefeitura-lanca-copa-salvador-interbairros-2026-com-40-times-e-participacao-inedita-de-equipes-femininas/ | N61: Copa Salvador Interbairros 2026, prevista de 30/08 a 06/12/2026, terá pela primeira vez uma categoria feminina, com dez equipes das regiões administrativas da capital. A inclusão foi apresentada pela Prefeitura como ação de ampliação de oportunidades para mulheres e construção do legado local da Copa Feminina 2027. A fonte não detalha os locais de todas as partidas. | O61: Ago | P61: 2026
A62: EVT-0091 | B62: Planejado | C62: 46264 | D62: SP | E62: São Paulo | F62: Festival e ativação de mídia | G62: Sportv / Nossa Arena | H62: 0 | I62: Sportv | J62: Nossa Arena | K62: -23.5505 | L62: -46.6333 | M62: https://www.meioemensagem.com.br/midia/sportv-faz-evento-para-celebrar-protagonismo-feminino | N62: Festival programado para 30/08/2026, das 9h às 13h, com atividades esportivas, debates, brunch e lançamento da campanha do Sportv sobre futebol feminino. A programação inclui bate-papo específico sobre a cobertura do canal para a Copa do Mundo Feminina 2027, com Alline Calandrini, Júlia Vergueiro e convidados, além da entrega de novos vestiários e apresentação de Alline como embaixadora do projeto. | O62: Ago | P62: 2026
A63: EVT-0082 | B63: Planejado | C63: 46270 | D63: POL | E63: Bielsko-Biała | F63: Seleções de Base | G63: FIFA / CBF / Seleção Brasileira Feminina Sub-20 | H63: 0 | J63: Estádio de Bielsko-Biała | M63: https://www.fifa.com/pt/tournaments/womens/u20womensworldcup/poland-2026 | N63: Copa do Mundo Feminina Sub-20 da FIFA Polônia 2026, disputada de 05 a 27/09/2026. O Brasil está no Grupo B e enfrenta Tanzânia (05/09), Canadá (08/09) e Inglaterra (11/09), sempre no Estádio de Bielsko-Biała, às 10h de Brasília. | O63: Set | P63: 2026
A64: EVT-0083 | B64: Planejado | C64: 46273 | D64: PRY | E64: Assunção | F64: Seleções de Base | G64: CONMEBOL / CBF / Seleção Brasileira Feminina Sub-15 | H64: 0 | J64: Local a definir | M64: https://www.cbf.com.br/selecao-brasileira/noticias/convocacoes-selecao-feminina-sub-15/a/beatriz-vaz-convoca-20-atletas-para-liga-evolucao-sub-15-da-conmebol | N64: A Seleção Brasileira Feminina Sub-15 busca o bicampeonato da CONMEBOL Liga Evolução, disputada de 08 a 20/09/2026 no Paraguai. A fonte confirma Assunção como cidade de referência, mas não informa o local físico dos jogos. | O64: Set | P64: 2026
A65: EVT-0022 | B65: Planejado | C65: 46279 | D65: RJ | E65: Rio de Janeiro | F65: Summit | G65: CONFUT / WIFS | H65: 0 | J65: Museu do Amanhã | K65: -22.8942 | L65: -43.1794 | M65: https://womanifs.com/ | N65: Women's International Football Summit (WIFS), encontro internacional dedicado ao futebol feminino, em 14 e 15/09/2026 no Museu do Amanhã. | O65: Set | P65: 2026
A66: EVT-0062 | B66: Planejado | C66: 46284 | D66: RJ | E66: Rio de Janeiro | F66: Tour histórico-cultural | G66: Tour Delas | H66: 0 | J66: Praça Tiradentes — ponto de encontro em frente ao VLT | K66: -22.9068 | L66: -43.1729 | M66: https://www.sympla.com.br/evento/historia-do-futebol-feminino-no-rio/3546698 | N66: Walking tour previsto para 19/09/2026, das 10h às 13h, pelo centro do Rio. O roteiro resgata a história do futebol feminino no Brasil, incluindo a proibição da modalidade, as pioneiras, a força dos coletivos de torcedoras e a Copa do Mundo Feminina 2027 como marco de um século de resistência. A realização depende de um mínimo de cinco participantes. | O66: Set | P66: 2026
A67: EVT-0084 | B67: Planejado | C67: 46287 | D67: RJ | E67: Teresópolis | F67: Seleções de Base | G67: CBF / Seleção Brasileira Feminina Sub-17 | H67: 0 | J67: Granja Comary | K67: -22.4167 | L67: -42.9782 | M67: https://www.cbf.com.br/selecao-brasileira/noticias/noticias/selecao-base-feminina/confira-o-calendario-do-segundo-semestre-das-selecoes-femininas-de-base | N67: Período de treinamento da Seleção Brasileira Feminina Sub-17 entre 22/09 e 16/10/2026, na Granja Comary, como preparação final para a Copa do Mundo da categoria no Marrocos. | O67: Set | P67: 2026
A68: EVT-0074 | B68: Planejado | C68: 46298 | D68: SP | E68: São Paulo | F68: Palestra | G68: COB Expo | H68: 0 | J68: Pro Magno Centro de Eventos | K68: -23.5505 | L68: -46.6333 | M68: https://cobexpo.soudaliga.com.br/reserva?date=2026-10-03&id=22500&nextInternalLocale=pt-BR | N68: Sessão “Copa do Mundo Feminina FIFA 2027 no Brasil: mídia, visibilidade e construção de legado”, em 03/10/2026, das 9h30 às 11h30, durante a COB Expo 2026. | O68: Out | P68: 2026 | Q68: 09:30 | R68: 11:30 | S68: America/Sao_Paulo
A69: EVT-0085 | B69: Planejado | C69: 46300 | D69: BR | E69: Local a definir | F69: Seleções de Base | G69: CBF / Seleção Brasileira Feminina Sub-20 | H69: 0 | J69: Local a definir | M69: https://www.cbf.com.br/selecao-brasileira/noticias/noticias/selecao-base-feminina/confira-o-calendario-do-segundo-semestre-das-selecoes-femininas-de-base | N69: Período de treinamentos da Seleção Brasileira Feminina Sub-20 previsto de 05 a 13/10/2026. A CBF não informou cidade nem local físico. | O69: Out | P69: 2026
A70: EVT-0086 | B70: Planejado | C70: 46312 | D70: MAR | E70: Local a definir | F70: Seleções de Base | G70: FIFA / CBF / Seleção Brasileira Feminina Sub-17 | H70: 0 | J70: Local a definir | M70: https://www.cbf.com.br/selecao-brasileira/noticias/noticias/selecao-base-feminina/confira-o-calendario-do-segundo-semestre-das-selecoes-femininas-de-base | N70: Copa do Mundo Feminina Sub-17 da FIFA, disputada de 17/10 a 07/11/2026 no Marrocos. O Brasil integra grupo com Canadá, Noruega e uma seleção africana; a fonte consultada não especifica cidade nem estádio. | O70: Out | P70: 2026
A71: EVT-0087 | B71: Planejado | C71: 46340 | D71: BR | E71: Local a definir | F71: Seleções de Base | G71: CBF / Seleção Brasileira Feminina Sub-15 | H71: 0 | J71: Local a definir | M71: https://www.cbf.com.br/selecao-brasileira/noticias/noticias/selecao-base-feminina/confira-o-calendario-do-segundo-semestre-das-selecoes-femininas-de-base | N71: Torneio Brasil de Seleções previsto de 14 a 22/11/2026 como encerramento do calendário da Seleção Feminina Sub-15. A fonte não informa cidade, local físico ou tabela de jogos. | O71: Nov | P71: 2026
A72: EVT-0055 | B72: Planejado | C72: 46341 | D72: SP | E72: São Paulo | F72: Premiação | G72: TV Brasil / EBC / Petrobras | H72: 0 | I72: Petrobras | J72: Local a definir | K72: -23.5505 | L72: -46.6333 | M72: https://www.ebc.com.br/premiotvbrasilpetrobrasparaelas/ | N72: Primeira edição do Prêmio TV Brasil Petrobras Para Elas, marcada para 15/11/2026, em São Paulo, com transmissão ao vivo pela TV Brasil e YouTube. A premiação reconhece atletas, treinadoras, clubes, departamentos e iniciativas relevantes para o fortalecimento do futebol feminino brasileiro. A fonte oficial confirma cidade e data, mas não informa o local físico. | O72: Nov | P72: 2026
A73: EVT-0088 | B73: Planejado | C73: 46350 | D73: BR | E73: Local a definir | F73: Seleções de Base | G73: CBF / Seleção Brasileira Feminina Sub-20 | H73: 0 | J73: Local a definir | M73: https://www.cbf.com.br/selecao-brasileira/noticias/noticias/selecao-base-feminina/confira-o-calendario-do-segundo-semestre-das-selecoes-femininas-de-base | N73: Janela de amistosos internacionais da Seleção Brasileira Feminina Sub-20 prevista entre 24/11 e 05/12/2026. Adversários, cidade e local físico ainda não foram divulgados. | O73: Nov | P73: 2026
A74: EVT-0011 | B74: Planejado | C74: 46357 | D74: BR | E74: Brasil | F74: Centro de Treinamento | G74: CBF / Seleção Brasileira Feminina | H74: 0 | J74: A definir | M74: Informado pelo usuário | N74: Definição do Team Base Camp prevista para dezembro de 2026. Data exata a definir. | O74: Dez | P74: 2026
A75: EVT-0089 | B75: Planejado | C75: 46362 | D75: BR | E75: Local a definir | F75: Seleções de Base | G75: CBF / Seleção Brasileira Feminina Sub-17 | H75: 0 | J75: Local a definir | M75: https://www.cbf.com.br/selecao-brasileira/noticias/noticias/selecao-base-feminina/confira-o-calendario-do-segundo-semestre-das-selecoes-femininas-de-base | N75: Período de treinamento da Seleção Brasileira Feminina Sub-17 previsto de 06 a 12/12/2026. A CBF não informou cidade nem local físico. | O75: Dez | P75: 2026
A76: EVT-0010 | B76: Planejado | C76: 46367 | D76: RJ | E76: Rio de Janeiro | F76: Sorteio Oficial | G76: FIFA | H76: 0 | J76: Museu de Arte Moderna do Rio de Janeiro (MAM Rio) | K76: -22.9068 | L76: -43.1729 | M76: https://www.fifa.com/pt/tournaments/womens/womensworldcup/brazil-2027/articles/sorteio-grupos-copa-mundo-feminina-2027-data-local | N76: Sorteio final dos grupos confirmado para 11/12/2026 no MAM Rio. O evento definirá os oito grupos e o caminho das 32 seleções na Copa do Mundo Feminina FIFA 2027. | O76: Dez | P76: 2026
A77: EVT-0008 | B77: Planejado | C77: 46444 | D77: BR | E77: Brasil | F77: Amistosos da Seleção | G77: CBF / Seleção Brasileira Feminina | H77: 0 | J77: A definir | M77: Informado pelo usuário | N77: Primeira janela de amistosos de 2027, de 26/02 a 06/03, voltada aos testes táticos finais antes da convocação. | O77: Fev | P77: 2027
A78: EVT-0090 | B78: Planejado | C78: 46478 | D78: BR | E78: Local a definir | F78: Ativação itinerante | G78: FIFA / cidades-sede | H78: 0 | J78: Local a definir | M78: https://www.correiodopovo.com.br/esportes/taca-da-copa-feminina-fara-tour-pelo-brasil-entre-abril-e-maio-de-2027-1.1742125 | N78: A FIFA anunciou durante o II Workshop de Cidades-Sede e Estádios que o Tour da Taça deve percorrer todas as cidades-sede entre abril e maio de 2027. O dia 01/04 foi usado apenas como data técnica para ordenação; as datas exatas, a ordem das cidades e os locais de exposição ainda serão definidos. | O78: Abr | P78: 2027
A79: EVT-0009 | B79: Planejado | C79: 46482 | D79: BR | E79: Brasil | F79: Data FIFA / Convocação | G79: CBF / Seleção Brasileira Feminina | H79: 0 | J79: A definir | M79: Informado pelo usuário | N79: Última Data FIFA oficial antes do Mundial, de 05 a 13/04/2027. Período previsto para Arthur Elias fechar a lista oficial de convocadas. | O79: Abr | P79: 2027
A80: EVT-0012 | B80: Planejado | C80: 46508 | D80: BR | E80: Brasil | F80: Preparação da Seleção | G80: CBF / Seleção Brasileira Feminina | H80: 0 | J80: Centro de treinamento a definir | K80: -22.9122 | L80: -43.2302 | M80: Informado pelo usuário | N80: Período de preparação fechada entre maio e junho de 2027, com concentração final e treinos intensivos sem interrupção de clubes. | O80: Mai | P80: 2027
A81: EVT-0077 | B81: Planejado | C81: 46548 | D81: RJ | E81: Rio de Janeiro | F81: Marco operacional | G81: FIFA / administração do Maracanã | H81: 0 | J81: Maracanã | K81: -22.9122 | L81: -43.2302 | M81: https://www.uol.com.br/esporte/futebol/ultimas-noticias/2026/08/24/cbf-garante-solucao-para-clubes-nao-perderem-mandos-na-copa-feminina.ghtm | N81: O Maracanã será o primeiro estádio entregue para uso exclusivo da FIFA, em 10/06/2027, 14 dias antes da abertura da Copa. As demais arenas terão início escalonado conforme a data de sua primeira partida; a fonte não publica aqui todas as datas individuais de entrega. | O81: Jun | P81: 2027
A82: EVT-0017 | B82: Planejado | C82: 46562 | D82: RJ | E82: Rio de Janeiro | F82: Jogo da Copa | G82: FIFA | H82: 0 | J82: Maracanã | K82: -22.9122 | L82: -43.2302 | M82: https://www.fifa.com/pt/articles/tabela-jogos-copa-feminina-divulgacao-maracana-final-abertura | N82: Partida de abertura da Copa e estreia do Brasil no Grupo A; adversário será definido no sorteio final. | O82: Jun | P82: 2027
A83: EVT-0018 | B83: Planejado | C83: 46567 | D83: SP | E83: São Paulo | F83: Jogo da Copa | G83: FIFA | H83: 0 | J83: Arena Itaquera | K83: -23.5453 | L83: -46.4742 | M83: https://www.fifa.com/pt/articles/tabela-jogos-copa-feminina-divulgacao-maracana-final-abertura | N83: Segundo jogo do Brasil na fase de grupos; adversário será definido no sorteio final. | O83: Jun | P83: 2027
A84: EVT-0019 | B84: Planejado | C84: 46572 | D84: DF | E84: Brasília | F84: Jogo da Copa | G84: FIFA | H84: 0 | J84: Estádio Nacional Mané Garrincha | K84: -15.7835 | L84: -47.8992 | M84: https://www.fifa.com/pt/articles/tabela-jogos-copa-feminina-divulgacao-maracana-final-abertura | N84: Terceiro jogo do Brasil na fase de grupos; adversário será definido no sorteio final. | O84: Jul | P84: 2027
A85: EVT-0020 | B85: Planejado | C85: 46593 | D85: RJ | E85: Rio de Janeiro | F85: Final da Copa | G85: FIFA | H85: 0 | J85: Maracanã | K85: -22.9122 | L85: -43.2302 | M85: https://www.fifa.com/pt/articles/tabela-jogos-copa-feminina-divulgacao-maracana-final-abertura | N85: Final da Copa do Mundo Feminina da FIFA Brasil 2027. | O85: Jul | P85: 2027
A86: EVT-0094 | B86: Planejado | C86: 46362 | D86: SP | E86: São Paulo | F86: Cultura / futebol feminino | G86: CCXP / Conspiração / Globo Filmes / TV Globo / Fox In The Snow | H86: 0 | J86: São Paulo Expo | M86: https://oglobo.globo.com/cultura/noticia/2026/09/02/marta-e-alice-carvalho-sao-confirmadas-em-painel-da-ccxp.ghtml | N86: Painel confirmado para 06/12/2026, último dia da CCXP26, com a presença de Marta e da atriz Alice Carvalho, que interpreta a jogadora em sua cinebiografia. O longa tem estreia prevista para abril de 2027, ano da Copa do Mundo Feminina no Brasil, ampliando a visibilidade cultural do futebol feminino no período de preparação para o torneio. | O86: Dez | P86: 2026
A87: EVT-20260907-DESFILE-COPA2027 | B87: Planejado | C87: 46272 | D87: DF | E87: Brasília | F87: Evento público / ativação institucional | G87: Governo Federal / Presidência da República | H87: 0 | J87: Esplanada dos Ministérios | K87: -15.7975 | L87: -47.8919 | M87: https://www1.folha.uol.com.br/blogs/brasilia-hoje/2026/09/lula-vai-usar-mote-a-forca-que-une-o-brasil-para-desfile-de-7-de-setembro.shtml | N87: O Desfile Cívico-Militar de 7 de Setembro de 2026, com início previsto às 9h na Esplanada dos Ministérios e acesso público gratuito às arquibancadas, terá a Copa do Mundo Feminina de 2027 como um dos três eixos temáticos oficiais da programação, ao lado de soberania nacional e enfrentamento à violência contra as mulheres. A programação divulgada prevê representação temática ligada ao Mundial e participação de atletas, conectando um dos maiores eventos públicos nacionais à promoção da Copa Feminina 2027. | O87: Set | P87: 2026
A88: EVT-0107 | B88: Planejado | C88: 46302 | D88: SP | E88: São Paulo | F88: Formação profissional | G88: FPF Academia / Federação Paulista de Futebol | H88: 0 | I88: Petrobras | J88: Edifício Pelé e atividades híbridas | K88: -23.5505 | L88: -46.6333 | M88: https://futebolpaulista.com.br/Noticias/Detalhe.aspx?Noticia=33167 | N88: Programa gratuito e exclusivo para mulheres voltado à formação de treinadoras e ao aumento da presença feminina em comissões técnicas. A 4ª edição ocorre de 07/10/2026 a 27/01/2027, com 78 horas de formação, aulas on-line, encontros presenciais, atividades práticas em campo e mentorias. As inscrições foram abertas em 03/09/2026. É editorialmente relevante para o Radar por fortalecer a qualificação profissional e o legado estrutural do futebol feminino no período de preparação para a Copa Feminina 2027. | O88: Out | P88: 2026
A89: EVT-ENFF-20260924 | B89: Planejado | C89: 46289 | D89: RS | E89: Porto Alegre | F89: Congresso / encontro setorial | G89: ENFF | H89: 0 | J89: Arena do Grêmio | K89: -30.0277 | L89: -51.2287 | M89: https://www.sympla.com.br/evento/enff/3495995 | N89: Encontro Nacional do Futebol Feminino previsto para 24 e 25/09/2026, na Arena do Grêmio, em Porto Alegre. A programação propõe conectar gestão, mercado, políticas públicas, marcas e oportunidades no futebol feminino, com foco especial no legado do Mundial Feminino de 2027 no Brasil. Item incluído por relevância direta para o ecossistema, ativações e oportunidades de engajamento ligadas à Copa 2027. | O89: Set | P89: 2026 | Q89: 08:00 | R89: 18:00 | S89: America/Sao_Paulo | T89: 46290
A90: EVT-0105 | B90: Realizado | C90: 46267 | D90: DF | E90: Brasília | F90: Encontro de impacto social | G90: Embaixada do Reino Unido / Secopa27 / Common Goal | H90: 0 | J90: Embaixada do Reino Unido | K90: -15.7939 | L90: -47.8828 | M90: https://blogs.correiobraziliense.com.br/dribledecorpo/a-294-dias-da-copa-inglaterra-debate-no-df-violencia-contra-a-mulher/ | N90: Encontro realizado em 02/09/2026 na Embaixada do Reino Unido, em Brasília, para debater soluções de enfrentamento à violência contra mulheres e meninas no contexto da preparação para a Copa do Mundo Feminina 2027. A programação teve abertura da secretária extraordinária Juliana Agatte e participação da Common Goal, que trabalha para usar o Mundial como plataforma de impacto social e equidade de gênero. | O90: Set | P90: 2026
A91: EVT-EDITORIAL-20260903-FUTEBOL-CIDADANIA | B91: Realizado | C91: 46268 | D91: BA | E91: Salvador | F91: Painel e debate | G91: SETRE Bahia / IPIE / UFBA | H91: 0 | J91: Colégio Estadual Professor Rômulo Almeida | K91: -12.9777 | L91: -38.5016 | M91: https://bahiaeconomica.com.br/wp/2026/09/03/painel-debate-futebol-feminino-e-lanca-inscricoes-para-voluntarios-da-copa-2027/ | N91: Painel realizado em 03/09/2026 com pesquisadores, representantes do esporte e comunidade escolar. O encontro debateu safeguarding e prevenção de abusos e assédios, apresentou diretrizes do voluntariado da Copa 2027 e discutiu legado do futebol feminino na Bahia, incluindo propostas de Centro de Referência do Futebol Feminino e formação de árbitras, treinadoras e gestoras. | O91: Set | P91: 2026
A92: evt-sesc-futebol-mulheres-20260915 | B92: Planejado | C92: 46280 | D92: SP | E92: São Paulo | F92: Curso / formação | G92: Sesc São Paulo — Centro de Pesquisa e Formação | H92: 0 | J92: Centro de Pesquisa e Formação do Sesc São Paulo | K92: -23.5505 | L92: -46.6333 | M92: https://www.sescsp.org.br/programacao/futebol-para-mulheres-entre-a-pratica-e-a-copa-modulo-2/ | N92: Módulo 2 do ciclo do Sesc sobre presença e protagonismo das mulheres no futebol brasileiro, com encontros em 15 e 17/09/2026, das 14h às 16h. A programação aborda gestão do futebol para mulheres e aspectos técnicos e fisiológicos, explicitamente no contexto que antecede e acompanha a Copa no Brasil. | O92: Set | P92: 2026
A93: SUG-rec9KbCAC206gEtAF | B93: Planejado | C93: 46297 | E93: Sao paulo | F93: Evento | H93: 0 | M93: https://www.instagram.com/p/DdOij3vIDWw/?stkn=bDAyNnJucWdoY3N3 | P93: 2026 | Q93: 17:00 | S93: America/Sao_Paulo
A94: CBF-2026-10-10-ARGENTINA | B94: Planejado | C94: 46305 | D94: RS | E94: Porto Alegre | F94: Amistoso da Seleção Feminina | G94: CBF | H94: 0 | J94: Beira-Rio | K94: -30.0654 | L94: -51.2365 | M94: https://news.google.com/rss/articles/CBMi4AFBVV95cUxOVGlGSW9BX09yWEhwMFFxVkROUUg4ZURKSWVITWhXOGt4Y2ppbGR3QThhTTVtX1lQZWxxTG8zcnJhZGRTd3JabHIwRlliTWZuRldoVEZIT0FuaUFnamhwLWdNN19GenBOYVVhNmtLWThabGpyem1vT0VjN3FOYnRXTjlLRGd4SXJGTkJCZ1Z3eHYzUElzRmRpVG9OaC1JVXZtVkw0bzh0bUFBQldsSTM5VklkMnktZ1lEU2dROVd3Q1VPeFY0NTJEQy00a3dPQ2xWcWY2cTAwMHMtQTQ3M2VSedIB4AFBVV95cUxOVGlGSW9BX09yWEhwMFFxVkROUUg4ZURKSWVITWhXOGt4Y2ppbGR3QThhTTVtX1lQZWxxTG8zcnJhZGRTd3JabHIwRlliTWZuRldoVEZIT0FuaUFnamhwLWdNN19GenBOYVVhNmtLWThabGpyem1vT0VjN3FOYnRXTjlLRGd4SXJGTkJCZ1Z3eHYzUElzRmRpVG9OaC1JVXZtVkw0bzh0bUFBQldsSTM5VklkMnktZ1lEU2dROVd3Q1VPeFY0NTJEQy00a3dPQ2xWcWY2cTAwMHMtQTQ3M2VSeQ?oc=5 | N94: Amistoso Brasil x Argentina confirmado; evento materializado independentemente da notícia. | O94: Out | P94: 2026 | Q94: 16:30 | S94: America/Sao_Paulo
A95: CBF-2026-10-13-ARGENTINA | B95: Planejado | C95: 46308 | D95: PE | E95: Recife | F95: Amistoso da Seleção Feminina | G95: CBF | H95: 0 | J95: Arena Pernambuco | K95: -8.0476 | L95: -34.877 | M95: https://news.google.com/rss/articles/CBMiuwFBVV95cUxONEpFakxFQkFRWVNsaEtUVC1KRHZNVXNxV2U4MkxucmtHckxpV2JOQ2ppMW03dmd0eVVxY2ZoRGFtRC1RSEtudzZTUXBfSGZQdEdYWnltMzlDS25tcTRiQUctT0thYWRwMGMwZjB6Nk9RVlRTRXhvVVRXTjNTZkpKWTktczc3YTNpSnhnVnNkNDI2NWVnbU52UHg5cVpMU2haUzUtMEVzS1cxRDNMd1paOFFsLUJQQm9XTVpv?oc=5 | N95: Amistoso Brasil x Argentina confirmado; evento materializado independentemente da notícia. | O95: Out | P95: 2026 | Q95: 20:30 | S95: America/Sao_Paulo
A96: WIFS-2027-06-23-RJ | B96: Planejado | C96: 46561 | D96: RJ | E96: Rio de Janeiro | F96: Ativação / evento Copa Feminina 2027 | G96: WIFS | H96: 0 | M96: https://womanifs.com/ | N96: Evento derivado de página-fonte; data e cidade validadas no conteúdo antes da materialização. | O96: Jun | P96: 2027
A97: WIFS-2027-07-06-PE | B97: Planejado | C97: 46574 | D97: PE | E97: Recife | F97: Ativação / evento Copa Feminina 2027 | G97: WIFS | H97: 0 | M97: https://womanifs.com/ | N97: Evento derivado de página-fonte; data e cidade validadas no conteúdo antes da materialização. | O97: Jul | P97: 2027
A98: WIFS-2027-07-09-CE | B98: Planejado | C98: 46577 | D98: CE | E98: Fortaleza | F98: Ativação / evento Copa Feminina 2027 | G98: WIFS | H98: 0 | M98: https://womanifs.com/ | N98: Evento derivado de página-fonte; data e cidade validadas no conteúdo antes da materialização. | O98: Jul | P98: 2027
A99: WIFS-2027-07-11-BA | B99: Planejado | C99: 46579 | D99: BA | E99: Salvador | F99: Ativação / evento Copa Feminina 2027 | G99: WIFS | H99: 0 | M99: https://womanifs.com/ | N99: Evento derivado de página-fonte; data e cidade validadas no conteúdo antes da materialização. | O99: Jul | P99: 2027
A100: WIFS-2027-06-27-RS | B100: Planejado | C100: 46565 | D100: RS | E100: Porto Alegre | F100: Ativação / evento Copa Feminina 2027 | G100: WIFS | H100: 0 | M100: https://womanifs.com/ | N100: Evento derivado de página-fonte; data e cidade validadas no conteúdo antes da materialização. | O100: Jun | P100: 2027
...

Sheet 03_Agenda
A1: Próximos Eventos | B1: Data | C1: Cidade | D1: UF | E1: Categoria | F1: Patrocinador | G1: Público | H1: Status
A2: {=_xlfn._xlws.FILTER(CHOOSE({1,2,3,4,5,6,7,8},'02_Eventos'!A2:A495,'02_Eventos'!C2:C495,'02_Eventos'!E2:E495,'02_Eventos'!D2:D495,'02_Eventos'!F2:F495,'02_Eventos'!I2:I495,'02_Eventos'!H2:H495,'02_Eventos'!B2:B495),('02_Eventos'!C2:C495>=TODAY())*('02_Eventos'!B2:B495<>"Cancelado"),"Sem eventos futuros")}
A3: EVT-0091
A4: EVT-0082
A5: EVT-0083
A6: EVT-0022
A7: EVT-0062
A8: EVT-0084
A9: EVT-0074
A10: EVT-0006
A11: EVT-0085
A12: EVT-0086
A13: EVT-0087
A14: EVT-0055
... A28: EVT-0020

Sheet 04_Radar_IAC
A1: Cidade | B1: UF | C1: Nº Eventos | D1: Público | E1: Patrocinadores | F1: Diversidade | G1: Eventos Oficiais | H1: Mídia | I1: Legado | J1: IAC | K1: Classificação
A2: Rio de Janeiro | B2: RJ | C2: =COUNTIF('02_Eventos'!E:E,A2) | D2: =SUMIF('02_Eventos'!E:E,A2,'02_Eventos'!H:H) | E2: =COUNTA(_xlfn.UNIQUE(_xlfn._xlws.FILTER('02_Eventos'!I:I,'02_Eventos'!E:E=A2,""))) | F2: =COUNTA(_xlfn.UNIQUE(_xlfn._xlws.FILTER('02_Eventos'!F:F,'02_Eventos'!E:E=A2,""))) | G2: 60 | H2: 55 | I2: 65 | J2: =MIN(100,(C2*5)+(MIN(D2/1000,20))+(E2*4)+(F2*3)+(G2*0.1)+(H2*0.1)+(I2*0.1)) | K2: =IF(J2>=85,"Excelente",IF(J2>=70,"Alta",IF(J2>=50,"Moderada",IF(J2>=30,"Baixa","Muito baixa"))))
A3: São Paulo | B3: SP | C3: =COUNTIF('02_Eventos'!E:E,A3) | D3: =SUMIF('02_Eventos'!E:E,A3,'02_Eventos'!H:H) | E3: =COUNTA(_xlfn.UNIQUE(_xlfn._xlws.FILTER('02_Eventos'!I:I,'02_Eventos'!E:E=A3,""))) | F3: =COUNTA(_xlfn.UNIQUE(_xlfn._xlws.FILTER('02_Eventos'!F:F,'02_Eventos'!E:E=A3,""))) | G3: 60 | H3: 55 | I3: 65 | J3: =MIN(100,(C3*5)+(MIN(D3/1000,20))+(E3*4)+(F3*3)+(G3*0.1)+(H3*0.1)+(I3*0.1)) | K3: =IF(J3>=85,"Excelente",IF(J3>=70,"Alta",IF(J3>=50,"Moderada",IF(J3>=30,"Baixa","Muito baixa"))))
A4: Belo Horizonte | B4: MG | C4: =COUNTIF('02_Eventos'!E:E,A4) | D4: =SUMIF('02_Eventos'!E:E,A4,'02_Eventos'!H:H) | E4: =COUNTA(_xlfn.UNIQUE(_xlfn._xlws.FILTER('02_Eventos'!I:I,'02_Eventos'!E:E=A4,""))) | F4: =COUNTA(_xlfn.UNIQUE(_xlfn._xlws.FILTER('02_Eventos'!F:F,'02_Eventos'!E:E=A4,""))) | G4: 60 | H4: 55 | I4: 65 | J4: =MIN(100,(C4*5)+(MIN(D4/1000,20))+(E4*4)+(F4*3)+(G4*0.1)+(H4*0.1)+(I4*0.1)) | K4: =IF(J4>=85,"Excelente",IF(J4>=70,"Alta",IF(J4>=50,"Moderada",IF(J4>=30,"Baixa","Muito baixa"))))
A5: Salvador | B5: BA | C5: =COUNTIF('02_Eventos'!E:E,A5) | D5: =SUMIF('02_Eventos'!E:E,A5,'02_Eventos'!H:H) | E5: =COUNTA(_xlfn.UNIQUE(_xlfn._xlws.FILTER('02_Eventos'!I:I,'02_Eventos'!E:E=A5,""))) | F5: =COUNTA(_xlfn.UNIQUE(_xlfn._xlws.FILTER('02_Eventos'!F:F,'02_Eventos'!E:E=A5,""))) | G5: 60 | H5: 55 | I5: 65 | J5: =MIN(100,(C5*5)+(MIN(D5/1000,20))+(E5*4)+(F5*3)+(G5*0.1)+(H5*0.1)+(I5*0.1)) | K5: =IF(J5>=85,"Excelente",IF(J5>=70,"Alta",IF(J5>=50,"Moderada",IF(J5>=30,"Baixa","Muito baixa"))))
A6: Recife | B6: PE | C6: =COUNTIF('02_Eventos'!E:E,A6) | D6: =SUMIF('02_Eventos'!E:E,A6,'02_Eventos'!H:H) | E6: =COUNTA(_xlfn.UNIQUE(_xlfn._xlws.FILTER('02_Eventos'!I:I,'02_Eventos'!E:E=A6,""))) | F6: =COUNTA(_xlfn.UNIQUE(_xlfn._xlws.FILTER('02_Eventos'!F:F,'02_Eventos'!E:E=A6,""))) | G6: 60 | H6: 55 | I6: 65 | J6: =MIN(100,(C6*5)+(MIN(D6/1000,20))+(E6*4)+(F6*3)+(G6*0.1)+(H6*0.1)+(I6*0.1)) | K6: =IF(J6>=85,"Excelente",IF(J6>=70,"Alta",IF(J6>=50,"Moderada",IF(J6>=30,"Baixa","Muito baixa"))))
A7: Fortaleza | B7: CE | C7: =COUNTIF('02_Eventos'!E:E,A7) | D7: =SUMIF('02_Eventos'!E:E,A7,'02_Eventos'!H:H) | E7: =COUNTA(_xlfn.UNIQUE(_xlfn._xlws.FILTER('02_Eventos'!I:I,'02_Eventos'!E:E=A7,""))) | F7: =COUNTA(_xlfn.UNIQUE(_xlfn._xlws.FILTER('02_Eventos'!F:F,'02_Eventos'!E:E=A7,""))) | G7: 60 | H7: 55 | I7: 65 | J7: =MIN(100,(C7*5)+(MIN(D7/1000,20))+(E7*4)+(F7*3)+(G7*0.1)+(H7*0.1)+(I7*0.1)) | K7: =IF(J7>=85,"Excelente",IF(J7>=70,"Alta",IF(J7>=50,"Moderada",IF(J7>=30,"Baixa","Muito baixa"))))
A8: Brasília | B8: DF | C8: =COUNTIF('02_Eventos'!E:E,A8) | D8: =SUMIF('02_Eventos'!E:E,A8,'02_Eventos'!H:H) | E8: =COUNTA(_xlfn.UNIQUE(_xlfn._xlws.FILTER('02_Eventos'!I:I,'02_Eventos'!E:E=A8,""))) | F8: =COUNTA(_xlfn.UNIQUE(_xlfn._xlws.FILTER('02_Eventos'!F:F,'02_Eventos'!E:E=A8,""))) | G8: 60 | H8: 55 | I8: 65 | J8: =MIN(100,(C8*5)+(MIN(D8/1000,20))+(E8*4)+(F8*3)+(G8*0.1)+(H8*0.1)+(I8*0.1)) | K8: =IF(J8>=85,"Excelente",IF(J8>=70,"Alta",IF(J8>=50,"Moderada",IF(J8>=30,"Baixa","Muito baixa"))))
A9: Porto Alegre | B9: RS | C9: =COUNTIF('02_Eventos'!E:E,A9) | D9: =SUMIF('02_Eventos'!E:E,A9,'02_Eventos'!H:H) | E9: =COUNTA(_xlfn.UNIQUE(_xlfn._xlws.FILTER('02_Eventos'!I:I,'02_Eventos'!E:E=A9,""))) | F9: =COUNTA(_xlfn.UNIQUE(_xlfn._xlws.FILTER('02_Eventos'!F:F,'02_Eventos'!E:E=A9,""))) | G9: 60 | H9: 55 | I9: 65 | J9: =MIN(100,(C9*5)+(MIN(D9/1000,20))+(E9*4)+(F9*3)+(G9*0.1)+(H9*0.1)+(I9*0.1)) | K9: =IF(J9>=85,"Excelente",IF(J9>=70,"Alta",IF(J9>=50,"Moderada",IF(J9>=30,"Baixa","Muito baixa"))))

Sheet 05_Radar_INP
A1: Cidade | B1: UF | C1: Infraestrutura | D1: Mobilidade | E1: Turismo | F1: Hospitalidade | G1: Voluntariado | H1: Comunicação | I1: Segurança | J1: INP | K1: Classificação
A2: Rio de Janeiro | B2: RJ | C2: 82 | D2: 78 | E2: 86 | F2: 84 | G2: 70 | H2: 76 | I2: 83 | J2: =AVERAGE(C2:I2) | K2: =IF(J2>=85,"Excelente",IF(J2>=70,"Alta",IF(J2>=50,"Moderada",IF(J2>=30,"Baixa","Muito baixa"))))
A3: São Paulo | B3: SP | C3: 88 | D3: 85 | E3: 90 | F3: 87 | G3: 72 | H3: 80 | I3: 86 | J3: =AVERAGE(C3:I3) | K3: =IF(J3>=85,"Excelente",IF(J3>=70,"Alta",IF(J3>=50,"Moderada",IF(J3>=30,"Baixa","Muito baixa"))))
A4: Belo Horizonte | B4: MG | C4: 76 | D4: 74 | E4: 79 | F4: 77 | G4: 68 | H4: 72 | I4: 80 | J4: =AVERAGE(C4:I4) | K4: =IF(J4>=85,"Excelente",IF(J4>=70,"Alta",IF(J4>=50,"Moderada",IF(J4>=30,"Baixa","Muito baixa"))))
A5: Salvador | B5: BA | C5: 72 | D5: 69 | E5: 82 | F5: 80 | G5: 65 | H5: 74 | I5: 78 | J5: =AVERAGE(C5:I5) | K5: =IF(J5>=85,"Excelente",IF(J5>=70,"Alta",IF(J5>=50,"Moderada",IF(J5>=30,"Baixa","Muito baixa"))))
A6: Recife | B6: PE | C6: 70 | D6: 68 | E6: 80 | F6: 78 | G6: 66 | H6: 71 | I6: 77 | J6: =AVERAGE(C6:I6) | K6: =IF(J6>=85,"Excelente",IF(J6>=70,"Alta",IF(J6>=50,"Moderada",IF(J6>=30,"Baixa","Muito baixa"))))
A7: Fortaleza | B7: CE | C7: 71 | D7: 70 | E7: 81 | F7: 79 | G7: 64 | H7: 70 | I7: 76 | J7: =AVERAGE(C7:I7) | K7: =IF(J7>=85,"Excelente",IF(J7>=70,"Alta",IF(J7>=50,"Moderada",IF(J7>=30,"Baixa","Muito baixa"))))
A8: Brasília | B8: DF | C8: 84 | D8: 82 | E8: 78 | F8: 80 | G8: 75 | H8: 79 | I8: 88 | J8: =AVERAGE(C8:I8) | K8: =IF(J8>=85,"Excelente",IF(J8>=70,"Alta",IF(J8>=50,"Moderada",IF(J8>=30,"Baixa","Muito baixa"))))
A9: Porto Alegre | B9: RS | C9: 74 | D9: 73 | E9: 76 | F9: 75 | G9: 69 | H9: 72 | I9: 79 | J9: =AVERAGE(C9:I9) | K9: =IF(J9>=85,"Excelente",IF(J9>=70,"Alta",IF(J9>=50,"Moderada",IF(J9>=30,"Baixa","Muito baixa"))))

Sheet 06_Noticias
A1: Data | B1: Título | C1: Tema | D1: Cidade/UF | E1: Veículo | F1: Link | G1: Sentimento | H1: Impacto | I1: Resumo
A2: 46315 | B2: CazéTV, Neooh e Helloo levam Copa do Mundo Feminina 2027 para o OOH - Máquina do Esporte | C2: Copa Feminina 2027 | D2: Brasil | E2: machinadoesporte.com.br | F2: https://news.google.com/rss/articles/CBMiwgFBVV95cUxPSFlPb19OcGZDQVJLbGhvVDZQX18zSUoxdjZLTEdUbDRsZlp3N3pmdUw3bkQ4S0hjRDd2MndYYnJra0pwRzFCN0l1OWQ5YU5FakZ2UTl1OXh5dVJLR0JfbVVWcmJ2R3V1VjlON1VIbUR1MkJDck5kYzZyTnhOZHd2YVhXV0VTcUhfSHNvQVlmekp6cUVtUnJPSTBTVWVVTldQU2ZWc01kUHZyalVJZjBDMTJfMm55QW1BNm9BZmoxNDBUQQ?oc=5 | G2: Neutro | H2: Médio | I2: Fonte: machinadoesporte.com.br. Descoberta via Google News; URL editorial direta não resolvida automaticamente.
A3: 46315 | B3: Sabrina Sato comandará “Abrindo o Jogo” no GNT antes da Copa do Mundo Feminina 2027 - MKT Esportivo | C3: Copa Feminina 2027 | D3: Brasil | E3: mktesportivo.com | F3: https://news.google.com/rss/articles/CBMiuwFBVV95cUxNdC0xN0lOQ0JjYUxOdjhkWG9JcFItNmIzZFVLN0hHeWNJOGRMNkIydWVlNFFiaXpvMzBBOWlTY29QaldPTVI2ZzJYRGwzZG02cVlyaDk2UkR0QVFUQmhrUWZZYjJsZEswdHlzZmVUVkRPcUFvQnJkcDQxdEJUaV85RDdFZEFEcVlRRENWcjNSZ1BObFpYeHcxaV9vcVM4VGwtRmlCanFVYkhsdkNJYWl4MXpXZjE1STBLTkpN?oc=5 | G3: Neutro | H3: Médio | I3: Fonte: mktesportivo.com. Descoberta via Google News; URL editorial direta não resolvida automaticamente.
A4: 46310 | B4: ‘Futebol feminino tem potencial comercial além da Copa de 2027’, diz executiva - Estadão | C4: Copa Feminina 2027 | D4: Brasil | E4: estadao.com.br | F4: https://news.google.com/rss/articles/CBMiwwFBVV95cUxOUGk2NHIxdW1tLXZ4b1Z0SU5CNE9paXZ2REpBTW1WTDJYeENKSnlQQl83ckdxcFFwOWp0Vm5SV2pEWFpzUmNEOFBwbmFzYlR3R1Raa2pNVnVxczVPN3c5RThfdHlzck5VandaZ1RidHcxUm1GTFNiYjQ2LWhlb1RZVnJHSE9ybE1uVklaWHB5U2ctVzdmNmN5UWgzRjhNRXRGaHlWUTRycGRmeHFaYk4zd2hWbUZGMjdnRWlHZ1BFRmdQSnPSAcgBQVVfeXFMTXI3WVZKaEtMWENRYU80eC1DYmM3WGxVUDh0Q0EzeVJoeTNlWV9vSmdhLUFRWjI3WU51LWExb053NEdoX1lZRFhkaGVoMTJKRk8tTm8yZjl2bjdCdG9USzdQaEpqNEFBOXFvLVdRN0pFTVJWeDdfdXAxcWs5STIzVzE0RGxLTWtRQmZHZXBnWVNvZHNONWh2eldvcWNEQUNnVGY3MEpmYVNTYXpuOWFPT2QwSGt2X0VvNmUwNndRSDJJQUhQUG1RcE0?oc=5 | G4: Neutro | H4: Médio | I4: Fonte: estadao.com.br. Descoberta via Google News; URL editorial direta não resolvida automaticamente.
A5: 46310 | B5: CBF negocia amistosos da Seleção só no Brasil antes da Copa de 2027 e planeja despedida; veja cidades - ge | C5: Copa Feminina 2027 | D5: Brasil | E5: ge.globo.com | F5: https://news.google.com/rss/articles/CBMigwJBVV95cUxQVmFXbFU5X09HeHZDTUt5amJsM1BHcWN1dWpyUUh4T0drWFpqNHFKSm5KR0R5akRfbUdWZk44VnBCZWtwaWZtOS1wczhraWgwLUVKeTdWZWtmYmt1b2pqUl9rclRGZ2dlekVqUVBYNUJnVGRTSWIzWjlDLU56X016ZWZFUDlBNndTNmktQ3N1YXluQUI1dXJuZFRhVGRxcHhfVFV3WE9NVnN1elppTjFDU25ia21UUk01WHpSS0JkeVJDN3FVV2NHWDJ3SlZUM05DSXBHU3RyeGxiR3dRNWNxYmtRYkRFaGhfZXJSS1dqMW9tQm4wYmhBVndReEV2RFVFSC1r0gGSAkFVX3lxTFB6ZWFWQ21ZeExuTmlfYmlnVjRtYlVCbkY5NWFpanB4TXpaaWY5QTBKQ09pbUZ4RWRRakoya1A4eUNDdkZrdUtJVEpFQTZ0bGp3S1JXT0VCUU1lVng0aXE2YWNvOUYybWxiYnNPTUY5WldQWGM5WWtkNDRRYVNzd0VyQk5OV05MVEN1MnNWbTctaUxXNWlxZ0Vpc2xfZGFKQ3NyYlZaZnRBSHA2NWg1T0pvQTBSdk0ycmUtZF9TYWdPTGhreUZwNlRKbEtoUWVnVTZKRkhXVmd4XzNOeFkwY0M3bERhcTdNbzBfbHZYSWZnMmdnWV9vRFBTZDgwUzJsdVBfRzJORTFlNU9DbmpqWC1MakE?oc=5 | G5: Neutro | H5: Médio | I5: Fonte: ge.globo.com. Descoberta via Google News; URL editorial direta não resolvida automaticamente.
A6: 46309 | B6: Luis Roberto volta à TV para narrar Copa do Mundo Feminina após tratar câncer - Estadão | C6: Copa Feminina 2027 | D6: Brasil | E6: estadao.com.br | F6: https://news.google.com/rss/articles/CBMitAFBVV95cUxQa01hMG9scG8yZXprdEtBd1FMQzZlZlZ1MVB0Q0RFN2RwaGJQYzZiaDVCWHY3a1JpTnNRYVN4RXBRTXpyN19QMm92YUNBSk0yeFlyYzBXdjFObDNQMjJVejB1M0w5VGxuVkZDdlhhUlk2RndTZGhYQ1UtSEpESTFKeXpJaWtLY1JtSmp1WTRUc2dtRTU3Yy1ubkVTSFR2Mm1hYm5nNE9kdURzcFQ4c0pKMnpFZ0rSAboBQVVfeXFMTWtZMFBTZ1RDNkVHWEx1ekJnbEJTYU5qakRBeUhITEZoNlJiZXlaWkM3aV8xcTVienBJbk9zdW9GSy1ZT2ZXREZQY1NERXRIZ3B2a1dKTGItVFU2WlloclVJWmZDT09yOWgxRzJtb0Z4YlVWVXpqb1BDUm85b1F4ZVJPMnF4TEM5b25PWXF2dWhkVVh3dUhBWjQzd3hKWmNZWjduMlNiXy1wQ1RXMUliWGJfLUVwcHFxX0JR?oc=5 | G6: Neutro | H6: Médio | I6: Fonte: estadao.com.br. Descoberta via Google News; URL editorial direta não resolvida automaticamente.
A7: 46309 | B7: Fifa testa operações para a Copa 2027 durante amistosos do Brasil que levaram 145 mil aos estádios - O TEMPO | C7: Copa Feminina 2027 | D7: Brasil | E7: otempo.com.br | F7: https://news.google.com/rss/articles/CBMi8AFBVV95cUxNNV9NZVA0MEctY1ZoeHBxSkZkYkltRW9DQ0syVWJrMUVwM3hQdU1wY3Q2dGZaYWl2dEtKTGJEVnZCRUVGUUpRLVZNZEFvUTNXd1YyT3pmVzM3d21oRWc0VHpyODJ2dHVtSGJtaUozWkxoeU9BY1IwdWYwWHlwLWtFYnRyeHNYQVFjSFZHakFJUWlsWXNPNDZaZ2FEeXdDeDJyMlJwMHZDa3dPZkhyOXpfNWdLcjFZc0RwM2hFSUFZM3RzWWF1VUJPc3lUWXVLTlQ4RW9IM0E5ZS1Jc2VMaXdXUkpQV19nbzFybHQydDRzc3M?oc=5 | G7: Neutro | H7: Médio | I7: Fonte: otempo.com.br. Descoberta via Google News; URL editorial direta não resolvida automaticamente.
A8: 46309 | B8: CBF se une a Ministérios em campanha contra violência de gênero e plano de legado para Copa Feminina - Máquina do Esporte | C8: Copa Feminina 2027 | D8: Brasil | E8: machinadoesporte.com.br | F8: https://news.google.com/rss/articles/CBMi5AFBVV95cUxNejB4MHRxYnhUeG1tVU1oTlhFUmQyNUNucVk3RkptOUFvdHBqRjlqZFowYjcyMFZ3UGN1cXpFeS05UjJDemNMLVp1M3dZcFN3Q01WQjhPV3FHLUI5TkdMMk1kT0tJaXZKT3hIWU8xRmtSRjBXbEJXWGNHNGlRWnpJWkIwUWRneG1NMDkxVktSN25OeFFwV2tmLXFjRlZRLVhhNzRTdkJxWk9kYkk2Tml4djdQdnZEeERPZVhQZnpjUkVpU0ZXX0Jwbk1WenQtUTRXOGJTTmlsdU5PSmJOZGluLW9FYkY?oc=5 | G8: Neutro | H8: Médio | I8: Fonte: machinadoesporte.com.br. Descoberta via Google News; URL editorial direta não resolvida automaticamente.
A9: 46309 | B9: FIFA acompanha amistoso do Brasil e prepara novidade para a Copa de 2027 - LANCE! | C9: Copa Feminina 2027 | D9: Brasil | E9: lance.com.br | F9: https://news.google.com/rss/articles/CBMiuwFBVV95cUxQRTNUMlRLUGxpYzhzUzhhRUxjT25tcHdnSGFYcFEtTy1mbW9aV1MxQi1SQkpsSU4wdFFNc3U1UXZ4X09TQXhhNmR6dFVmbzBfVG1vNTVKS014dXRqcFFGWEdibzFKaUkyLTFqaHJYaXdsZDlPQXNlMkMzM1c0aVFlb2F4cDF5TjZXa3hsd0QybWVwYmFSN1ZXWXhScGF3eEhvVlhIenc1bkV5VU9IeGE4dk1TdDRoaVk2UkRj?oc=5 | G9: Neutro | H9: Médio | I9: Fonte: lance.com.br. Descoberta via Google News; URL editorial direta não resolvida automaticamente.
A10: 46309 | B10: "Momento dela": Arthur Elias projeta Marta na Copa do Mundo Feminina 2027 - CNN Brasil | C10: Copa Feminina 2027 | D10: Brasil | E10: cnnbrasil.com.br | F10: https://news.google.com/rss/articles/CBMiywFBVV95cUxPTVcwbFRwUkJOSUsyUlB3bUVmZHJaTENlcXlwZHdlamZpbklIbEdKdkRBMUpSZG5zVFgtNG1Kdm9ZWWNGTGVtbTJ3NnhJNmYwVmdyaDRDVTBrTzdENUR5OWwzYWpBeWZDc2ZaRXFrcE95Z0d0aW9wWG1TMFZMOTdhdFFGcHJFblZLTGJ2YVloN0RFakd1dGE5MktoaW1SQ1UyX0w4MDNkNEJ6cHB5Z1FENkRVWWxxUlJNYmYtYVFVcDZtcE4wWUpFaHR5WQ?oc=5 | G10: Neutro | H10: Médio | I10: Fonte: cnnbrasil.com.br. Descoberta via Google News; URL editorial direta não resolvida automaticamente.
A11: 46309 | B11: Copa do Mundo Feminina de 2027 abre oportunidades para turismo e comércio no RS - Correio do Povo | C11: Copa Feminina 2027 | D11: Brasil | E11: correiodopovo.com.br | F11: https://news.google.com/rss/articles/CBMi3gFBVV95cUxOX1lFTDFpeVltaktpNTJqeFlSMnktYjF2N2JjeHpYcHNNSzZhQ1J2MHVDYmN1ZkVMcFdpNXdzM296UXZfXzFGWFBiYUs3ZzNhT3VEeWlIU2NwQ2NsZHVuVk9DTGlTb3FmbDQyVHdSMllITHBmREs0VE9iWlFGbUhPV0x5c080ODd6YzFkd2xmdnk3dWMyazY5bGhJZlVydnpRRDVlb25XMG02TElYNVNlOTlwNm9tdjBrNlFsU1dBMEp2cnFHbGhkc2toV19jQVhoX2t0VXRhYWRlV2ljdGc?oc=5 | G11: Neutro | H11: Médio | I11: Fonte: correiodopovo.com.br. Descoberta via Google News; URL editorial direta não resolvida automaticamente.
A12: 46308 | B12: Debate sobre impactos da Copa 2027 aponta oportunidades para empresas e turismo - Prefeitura de Porto Alegre | C12: Copa Feminina 2027 | D12: Brasil | E12: prefeitura.poa.br | F12: https://news.google.com/rss/articles/CBMiwwFBVV95cUxNRV9VTWZvb21DRUVZNVN3NEhKaV90c3hrLU9DSk5RQXgwb0dORWoyUDJ0ZUw0RV9SY1A0Yll1REY4QVBGVkNRQmxLRE9TcWRVUkRIZ1B4T2NnMXpRZGFBRHNUOGZIcFp3c1N1T0tIaEVYcmdiU3dkLWM3WkRQOWp1MEdoSDdnNkxlUXZZMXRaSUZZbWs1LVcyN3B2SGpDOENVZWZqakVnektpUmN5XzR0TUNfRndoYmdPRE9qVzd4ai1vMDg?oc=5 | G12: Neutro | H12: Médio | I12: Fonte: prefeitura.poa.br. Descoberta via Google News; URL editorial direta não resolvida automaticamente.
A13: 46305 | B13: Porto Alegre recebe a Seleção Brasileira Feminina em amistoso contra a Argentina neste sábado - Prefeitura de Porto Alegre | C13: Copa Feminina 2027 | D13: Brasil | E13: prefeitura.poa.br | F13: https://news.google.com/rss/articles/CBMivwFBVV95cUxOOXpCcGg4bnV5ZjM5eDdKZ21NZWVZNnFCVzNXa1FiY1dsTmdfLVh0enpwd0pBZ2E5THRmM1N4MnlnS28yYkx3VzR3LWVFUVhhdjI1VDQ5Ul8tWF9hdm1CazhLVVVnVWZCd0I2eXdtT2RKVkctenhzLUdvd2NVeDBtenJHQWV2U2NCVkJ6Q0o5LXJTUXFFc090SUt0bjZzV3NhX09LYm5sTExqeHBHdFdhYjVEcnN3b1Zpc3NpUllBRQ?oc=5 | G13: Neutro | H13: Médio | I13: Fonte: prefeitura.poa.br. Descoberta via Google News; URL editorial direta não resolvida automaticamente.
... A188: 46278 | B188: Câmara aprova férias escolares facultativas durante Copa do Mundo Feminina de 2027 - O GLOBO | C188: Copa Feminina 2027 | D188: Brasil | E188: oglobo.globo.com | F188: https://oglobo.globo.com/brasil/noticia/2026/09/01/camara-aprova-ferias-escolares-facultativas-durante-copa-do-mundo-feminina-de-2027.ghtml | G188: Neutro | H188: Médio | I188: A Câmara dos Deputados aprovou, nesta segunda-feira (31), regras que permitem às escolas decidir se querem ajustar o calendário de férias durante a Copa do Mundo Feminina de 2027. A proposta, que busca preservar a autonomia dos sistemas de ensino, segue agora para análise do Senado. O texto é um substitutivo do deputado Alex Manente (Cidadania-SP) ao Projeto de Lei 3.481/26, da deputada Any Ortiz (PP-RS).
A189: 46277 | B189: A 9 meses da Copa do Mundo, TVs já apostam em programas de futebol feminino | C189: Copa Feminina 2027 | D189: Brasil | E189: noticiasdatv.uol.com.br | F189: https://noticiasdatv.uol.com.br/noticia/televisao/a-9-meses-da-copa-do-mundo-tvs-ja-apostam-em-programas-de-futebol-feminino-156477 | G189: Neutro | H189: Médio
A190: 46252 | B190: CNE orienta ajustes no calendário escolar durante a Copa Feminina 2027 | C190: Educação / calendário escolar / cidades-sede / operação da Copa 2027 | D190: Brasil | E190: MEC / CNE | F190: https://www.gov.br/mec/pt-br/assuntos/noticias/2026/agosto/cne-orienta-redes-de-ensino-sobre-organizacao-do-calendario-escolar-durante-a-copa-do-mundo-feminina-de-2027 | G190: Neutro | H190: Alto | I190: O Conselho Nacional de Educação aprovou o Parecer CNE/CEB nº 7/2026 orientando os sistemas de ensino sobre a organização dos calendários escolares de 2027 em razão da Copa do Mundo Feminina. Cidades-sede, regiões metropolitanas e áreas diretamente impactadas deverão promover os ajustes necessários conforme a realidade local e o calendário oficial da competição.
A191: 46276 | B191: Maracanã trocará gramado em 2027 antes da Copa do Mundo Feminina | C191: Rio de Janeiro / Maracanã / gramado / infraestrutura / Copa Feminina 2027 | D191: Rio de Janeiro/RJ | E191: UOL | F191: https://www.uol.com.br/esporte/futebol/ultimas-noticias/2026/09/11/maracana-aponta-fatores-para-campo-ruim-e-informa-que-trocara-tipo-de-grama.ghtm | G191: Neutro | H191: Alto | I191: A administração do Maracanã informou que substituirá o gramado atual por Celebration Hybrid em 2027. A mudança ocorre em um ano de calendário intenso no estádio, que receberá partidas da Copa do Mundo Feminina, incluindo a abertura e a final do torneio, e busca melhorar a qualidade do campo após críticas recorrentes.
A192: 46275 | B192: Debate cobra legado duradouro da Copa Feminina 2027 para mulheres no esporte | C192: Legado social / futebol feminino / políticas públicas / Copa Feminina 2027 | D192: Brasil | E192: UOL | F192: https://noticias.uol.com.br/colunas/joildo-santos/2026/09/10/a-copa-das-mulheres-vai-deixar-um-legado-ou-apenas-uma-fotografia.ghtm | G192: Neutro | H192: Médio | I192: Artigo publicado em 10/09/2026 discute se a Copa do Mundo Feminina de 2027 deixará legado estrutural para mulheres no esporte, defendendo investimentos permanentes em infraestrutura, formação, acesso à modalidade e políticas de proteção e equidade, para que o impacto do torneio ultrapasse a realização dos jogos.
A193: 46275 | B193: CBF prevê pausa no futebol masculino durante a Copa Feminina 2027 | C193: Calendário CBF / operação dos estádios / Copa Feminina 2027 | D193: Brasil | E193: UOL | F193: https://www.uol.com.br/esporte/futebol/colunas/rodrigo-mattos/2026/09/10/o-que-se-sabe-sobre-o-calendario-do-futebol-para-2027.ghtm | G193: Neutro | H193: Alto | I193: A CBF prepara o calendário de 2027 prevendo paralisação do futebol masculino durante a Copa do Mundo Feminina e ajustes cerca de 15 dias antes do início do torneio para liberar os estádios cedidos à FIFA. A medida afeta diretamente a operação de arenas como Maracanã, Arena Itaquera, Beira-Rio, Mineirão e Arena Salvador durante o Mundial.
A194: 46274 | B194: Estádio Presidente Vargas recebe visita técnica da FIFA e avança nos preparativos para 2027 | C194: Fortaleza / estádio de apoio / inspeção FIFA / operação da Copa 2027 | D194: Fortaleza/CE | E194: Portal IN | F194: https://www.portalin.com.br/in-loco/estadio-presidente-vargas-recebe-visita-tecnica-da-fifa-e-avanca-os-preparativos/ | G194: Positivo | H194: Médio | I194: O Estádio Presidente Vargas, em Fortaleza, recebeu visita técnica da FIFA para avaliação de estrutura, logística e operação ligadas à Copa do Mundo Feminina 2027. O equipamento deve integrar a estrutura de apoio da cidade-sede, ao lado da Arena Castelão, atendendo delegações e operações do torneio.
A195: 46275 | B195: CBF vê Copa Feminina 2027 como teste para Mundial de Clubes de 2029 no Brasil | C195: CBF / estratégia internacional / Copa Feminina 2027 / Mundial de Clubes 2029 | D195: Brasil | E195: Lance! | F195: https://www.lance.com.br/futebol-feminino/cbf-ve-copa-do-mundo-feminina-como-teste-para-mundial-de-clubes-de-2029-no-brasil.html | G195: Positivo | H195: Médio | I195: A CBF trata a organização da Copa do Mundo Feminina de 2027 no Brasil como referência e teste para projetos internacionais futuros, incluindo a possibilidade de receber um Mundial de Clubes em 2029. A pauta destaca iniciativas em discussão e a construção de uma estratégia de longo prazo ligada à realização do torneio feminino no país.
A196: 46274 | B196: FIFA faz visita técnica ao Estádio Presidente Vargas nos preparativos para a Copa Feminina 2027 | C196: Fortaleza / centro de treinamento / infraestrutura / preparação da Copa 2027 | D196: Fortaleza/CE | E196: Prefeitura de Fortaleza | F196: https://fortaleza.ce.gov.br/noticias/nos-preparativos-para-a-copa-do-mundo-feminina-da-fifa-brasil-2027-estadio-presidente-vargas-recebe-visita-tecnica-da-entidade | G196: Positivo | H196: Médio | I196: O Estádio Presidente Vargas, em Fortaleza, recebeu em 04/09/2026 uma visita técnica da FIFA. A equipe avaliou instalações e a organização de espaços que poderão atender delegações e imprensa durante a Copa do Mundo Feminina FIFA 2027, reforçando a preparação da cidade-sede.
A197: 46275 | B197: CBF prepara calendário de 2027 com pausa e adaptação de estádios para a Copa Feminina | C197: Calendário CBF / clubes / estádios / operação da Copa 2027 | D197: Brasil | E197: UOL | F197: https://www.uol.com.br/esporte/futebol/colunas/rodrigo-mattos/2026/09/10/o-que-se-sabe-sobre-o-calendario-do-futebol-para-2027.htm | G197: Neutro | H197: Alto | I197: A CBF prepara o calendário do futebol brasileiro de 2027 considerando a paralisação do futebol masculino durante a Copa do Mundo Feminina e ajustes cerca de 15 dias antes do torneio para evitar jogos nos estádios cedidos à FIFA. A medida afeta arenas como Maracanã, Neo Química Arena, Beira-Rio e Mineirão.
A198: 46274 | B198: Governo negocia ingressos populares para a Copa do Mundo Feminina 2027 | C198: Ingressos / acesso / organização da Copa 2027 | D198: Brasil | E198: ge | F198: https://ge.globo.com/futebol/copa-do-mundo/noticia/2026/09/09/copa-feminina-governo-negocia-ingressos-populares-e-cre-em-torneio-blindado-da-crise-na-fifa.ghtml | G198: Positivo | H198: Alto | I198: O Governo Federal negocia com a FIFA uma cota de ingressos a preços populares para a Copa do Mundo Feminina de 2027 no Brasil. A pauta também envolve transporte, segurança, legado, calendário e medidas para ampliar o acesso do público aos estádios durante o torneio.
A199: 46267 | B199: Pernambuco sanciona lei estadual para operação da Copa Feminina 2027 | C199: Recife / legislação estadual / mobilidade / segurança / operação da Copa 2027 | D199: Recife/PE | E199: Alepe Legis | F199: https://legis.alepe.pe.gov.br/texto.aspx?id=89825&tipo= | G199: Positivo | H199: Alto | I199: Sancionada em 1º/09 e publicada no Diário Oficial em 2/09, a Lei nº 19.341/2026 estabelece as medidas estaduais para viabilizar a Copa Feminina 2027 em Pernambuco. A norma disciplina cooperação institucional, proteção comercial, controle de acesso, segurança, mobilidade, tramitação prioritária de licenças, hidratação do público e ações de turismo, futebol feminino e legado social.
A200: 46273 | B200: Lorena é indicada ao prêmio de melhor goleira da Bola de Ouro 2026 | C200: Seleção Brasileira / Lorena / Bola de Ouro 2026 / ciclo da Copa Feminina 2027 | D200: Internacional | E200: CNN Brasil | F200: https://www.cnnbrasil.com.br/esportes/futebol/futebol-internacional/bola-de-ouro-lorena-e-indicada-a-melhor-goleira-do-futebol-feminino/ | G200: Positivo | H200: Médio | I200: Lorena, goleira titular da Seleção Brasileira principal e atleta do Kansas City, foi indicada em 08/09/2026 ao prêmio de melhor goleira do futebol feminino da Bola de Ouro 2026. O reconhecimento internacional integra o acompanhamento das principais atletas brasileiras no ciclo de preparação para a Copa do Mundo Feminina FIFA 2027 no Brasil.
A201: 46254 | B201: São Paulo terá 10 jogos da Copa Feminina 2027 e prepara mobilidade, turismo e legado | C201: São Paulo / calendário / Arena Itaquera / mobilidade / turismo / legado / Copa 2027 | D201: São Paulo/SP | E201: Prefeitura de São Paulo | F201: https://www2.prefeitura.sp.gov.br/web/prefeitura-de-sao-paulo/w/cidade-com-mais-jogos-s%C3%A3o-paulo-receber%C3%A1-10-partidas-da-copa-do-mundo-feminina-2027 | G201: Positivo | H201: Alto | I201: A Prefeitura de São Paulo detalhou em 20/08/2026 o calendário da cidade para a Copa do Mundo Feminina 2027. A capital receberá 10 das 64 partidas, o maior número entre as oito sedes, incluindo seis jogos de fase de grupos, a partida da Seleção Brasileira em 29/06/2027, uma oitava de final, uma quarta de final, uma semifinal e a disputa do terceiro lugar na Arena Itaquera.
... A278: 46199 | B278: CBF divulga calendário do segundo semestre das Seleções Femininas de Base | C278: Seleções de Base / calendário 2026 | D278: Brasil e exterior | E278: CBF | F278: https://www.cbf.com.br/selecao-brasileira/noticias/noticias/selecao-base-feminina/confira-o-calendario-do-segundo-semestre-das-selecoes-femininas-de-base | G278: Neutro | H278: Alto | I278: O calendário oficial reúne Liga Evolução Sub-15, Copas do Mundo Sub-17 e Sub-20, períodos de treinamento, Torneio Brasil e amistosos internacionais entre junho e dezembro de 2026.

Sheet 07_Mapa_Base
A1: Cidade | B1: UF | C1: Latitude | D1: Longitude | E1: IAC | F1: INP | G1: Eventos | H1: Público
A2: Rio de Janeiro | B2: RJ | C2: -22.9068 | D2: -43.1729 | E2: =_xludf.XLOOKUP(A2,'04_Radar_IAC'!A:A,'04_Radar_IAC'!J:J,0) | F2: =_xludf.XLOOKUP(A2,'05_Radar_INP'!A:A,'05_Radar_INP'!J:J,0) | G2: =COUNTIF('02_Eventos'!E:E,A2) | H2: =SUMIF('02_Eventos'!E:E,A2,'02_Eventos'!H:H)
A3: São Paulo | B3: SP | C3: -23.5505 | D3: -46.6333 | E3: =_xludf.XLOOKUP(A3,'04_Radar_IAC'!A:A,'04_Radar_IAC'!J:J,0) | F3: =_xludf.XLOOKUP(A3,'05_Radar_INP'!A:A,'05_Radar_INP'!J:J,0) | G3: =COUNTIF('02_Eventos'!E:E,A3) | H3: =SUMIF('02_Eventos'!E:E,A3,'02_Eventos'!H:H)
A4: Belo Horizonte | B4: MG | C4: -19.9167 | D4: -43.9345 | E4: =_xludf.XLOOKUP(A4,'04_Radar_IAC'!A:A,'04_Radar_IAC'!J:J,0) | F4: =_xludf.XLOOKUP(A4,'05_Radar_INP'!A:A,'05_Radar_INP'!J:J,0) | G4: =COUNTIF('02_Eventos'!E:E,A4) | H4: =SUMIF('02_Eventos'!E:E,A4,'02_Eventos'!H:H)
A5: Salvador | B5: BA | C5: -12.9777 | D5: -38.5016 | E5: =_xludf.XLOOKUP(A5,'04_Radar_IAC'!A:A,'04_Radar_IAC'!J:J,0) | F5: =_xludf.XLOOKUP(A5,'05_Radar_INP'!A:A,'05_Radar_INP'!J:J,0) | G5: =COUNTIF('02_Eventos'!E:E,A5) | H5: =SUMIF('02_Eventos'!E:E,A5,'02_Eventos'!H:H)
A6: Recife | B6: PE | C6: -8.0476 | D6: -34.877 | E6: =_xludf.XLOOKUP(A6,'04_Radar_IAC'!A:A,'04_Radar_IAC'!J:J,0) | F6: =_xludf.XLOOKUP(A6,'05_Radar_INP'!A:A,'05_Radar_INP'!J:J,0) | G6: =COUNTIF('02_Eventos'!E:E,A6) | H6: =SUMIF('02_Eventos'!E:E,A6,'02_Eventos'!H:H)
A7: Fortaleza | B7: CE | C7: -3.7319 | D7: -38.5267 | E7: =_xludf.XLOOKUP(A7,'04_Radar_IAC'!A:A,'04_Radar_IAC'!J:J,0) | F7: =_xludf.XLOOKUP(A7,'05_Radar_INP'!A:A,'05_Radar_INP'!J:J,0) | G7: =COUNTIF('02_Eventos'!E:E,A7) | H7: =SUMIF('02_Eventos'!E:E,A7,'02_Eventos'!H:H)
A8: Brasília | B8: DF | C8: -15.7939 | D8: -47.8828 | E8: =_xludf.XLOOKUP(A8,'04_Radar_IAC'!A:A,'04_Radar_IAC'!J:J,0) | F8: =_xludf.XLOOKUP(A8,'05_Radar_INP'!A:A,'05_Radar_INP'!J:J,0) | G8: =COUNTIF('02_Eventos'!E:E,A8) | H8: =SUMIF('02_Eventos'!E:E,A8,'02_Eventos'!H:H)
A9: Porto Alegre | B9: RS | C9: -30.0346 | D9: -51.2177 | E9: =_xludf.XLOOKUP(A9,'04_Radar_IAC'!A:A,'04_Radar_IAC'!J:J,0) | F9: =_xludf.XLOOKUP(A9,'05_Radar_INP'!A:A,'05_Radar_INP'!J:J,0) | G9: =COUNTIF('02_Eventos'!E:E,A9) | H9: =SUMIF('02_Eventos'!E:E,A9,'02_Eventos'!H:H)

Sheet 08_Patrocinadores
A1: Patrocinador | B1: Segmento | C1: Status | D1: Nº Ativações | E1: Público Alcançado | F1: Cidades | G1: Investimento Estimado | H1: Observações
A2: Visa | B2: Serviços financeiros | C2: Ativo | D2: =COUNTIF('02_Eventos'!I:I,A2) | E2: =SUMIF('02_Eventos'!I:I,A2,'02_Eventos'!H:H) | F2: =COUNTA(_xlfn.UNIQUE(_xlfn._xlws.FILTER('02_Eventos'!E:E,'02_Eventos'!I:I=A2,""))) | G2: 0
A3: Adidas | B3: Material esportivo | C3: Ativo | D3: =COUNTIF('02_Eventos'!I:I,A3) | E3: =SUMIF('02_Eventos'!I:I,A3,'02_Eventos'!H:H) | F3: =COUNTA(_xlfn.UNIQUE(_xlfn._xlws.FILTER('02_Eventos'!E:E,'02_Eventos'!I:I=A3,""))) | G3: 0
A4: Itaú | B4: Banco | C4: Ativo | D4: =COUNTIF('02_Eventos'!I:I,A4) | E4: =SUMIF('02_Eventos'!I:I,A4,'02_Eventos'!H:H) | F4: =COUNTA(_xlfn.UNIQUE(_xlfn._xlws.FILTER('02_Eventos'!E:E,'02_Eventos'!I:I=A4,""))) | G4: 0
A5: Coca-Cola | B5: Bebidas | C5: Ativo | D5: =COUNTIF('02_Eventos'!I:I,A5) | E5: =SUMIF('02_Eventos'!I:I,A5,'02_Eventos'!H:H) | F5: =COUNTA(_xlfn.UNIQUE(_xlfn._xlws.FILTER('02_Eventos'!E:E,'02_Eventos'!I:I=A5,""))) | G5: 0
A6: Banco do Brasil | B6: Banco | C6: Prospect | D6: =COUNTIF('02_Eventos'!I:I,A6) | E6: =SUMIF('02_Eventos'!I:I,A6,'02_Eventos'!H:H) | F6: =COUNTA(_xlfn.UNIQUE(_xlfn._xlws.FILTER('02_Eventos'!E:E,'02_Eventos'!I:I=A6,""))) | G6: 0

Sheet 09_Cidades
A1: Cidade | B1: UF | C1: Região | D1: População | E1: Estádio/Arena | F1: Aeroporto | G1: IAC | H1: INP | I1: Eventos | J1: Observações
A2: Rio de Janeiro | B2: RJ | C2: Sudeste | D2: 0 | E2: A definir | F2: A definir | G2: =_xludf.XLOOKUP(A2,'04_Radar_IAC'!A:A,'04_Radar_IAC'!J:J,0) | H2: =_xludf.XLOOKUP(A2,'05_Radar_INP'!A:A,'05_Radar_INP'!J:J,0) | I2: =COUNTIF('02_Eventos'!E:E,A2)
A3: São Paulo | B3: SP | C3: Sudeste | D3: 0 | E3: A definir | F3: A definir | G3: =_xludf.XLOOKUP(A3,'04_Radar_IAC'!A:A,'04_Radar_IAC'!J:J,0) | H3: =_xludf.XLOOKUP(A3,'05_Radar_INP'!A:A,'05_Radar_INP'!J:J,0) | I3: =COUNTIF('02_Eventos'!E:E,A3)
A4: Belo Horizonte | B4: MG | C4: Sudeste | D4: 0 | E4: A definir | F4: A definir | G4: =_xludf.XLOOKUP(A4,'04_Radar_IAC'!A:A,'04_Radar_IAC'!J:J,0) | H4: =_xludf.XLOOKUP(A4,'05_Radar_INP'!A:A,'05_Radar_INP'!J:J,0) | I4: =COUNTIF('02_Eventos'!E:E,A4)
A5: Salvador | B5: BA | C5: Nordeste | D5: 0 | E5: A definir | F5: A definir | G5: =_xludf.XLOOKUP(A5,'04_Radar_IAC'!A:A,'04_Radar_IAC'!J:J,0) | H5: =_xludf.XLOOKUP(A5,'05_Radar_INP'!A:A,'05_Radar_INP'!J:J,0) | I5: =COUNTIF('02_Eventos'!E:E,A5)
A6: Recife | B6: PE | C6: Nordeste | D6: 0 | E6: A definir | F6: A definir | G6: =_xludf.XLOOKUP(A6,'04_Radar_IAC'!A:A,'04_Radar_IAC'!J:J,0) | H6: =_xludf.XLOOKUP(A6,'05_Radar_INP'!A:A,'05_Radar_INP'!J:J,0) | I6: =COUNTIF('02_Eventos'!E:E,A6)
A7: Fortaleza | B7: CE | C7: Nordeste | D7: 0 | E7: A definir | F7: A definir | G7: =_xludf.XLOOKUP(A7,'04_Radar_IAC'!A:A,'04_Radar_IAC'!J:J,0) | H7: =_xludf.XLOOKUP(A7,'05_Radar_INP'!A:A,'05_Radar_INP'!J:J,0) | I7: =COUNTIF('02_Eventos'!E:E,A7)
A8: Brasília | B8: DF | C8: Centro-Oeste | D8: 0 | E8: A definir | F8: A definir | G8: =_xludf.XLOOKUP(A8,'04_Radar_IAC'!A:A,'04_Radar_IAC'!J:J,0) | H8: =_xludf.XLOOKUP(A8,'05_Radar_INP'!A:A,'05_Radar_INP'!J:J,0) | I8: =COUNTIF('02_Eventos'!E:E,A8)
A9: Porto Alegre | B9: RS | C9: Sul | D9: 0 | E9: A definir | F9: A definir | G9: =_xludf.XLOOKUP(A9,'04_Radar_IAC'!A:A,'04_Radar_IAC'!J:J,0) | H9: =_xludf.XLOOKUP(A9,'05_Radar_INP'!A:A,'05_Radar_INP'!J:J,0) | I9: =COUNTIF('02_Eventos'!E:E,A9)

Sheet 10_Legado
A1: ID | B1: Projeto | C1: Cidade/UF | D1: Eixo | E1: Responsável | F1: Início | G1: Fim | H1: Status | I1: Beneficiários | J1: Resultado Esperado
A2: LEG-001 | B2: Futebol para Meninas | C2: Rio de Janeiro/RJ | D2: Social | E2: ONG Parceira | F2: 46235 | G2: 46600 | H2: Em execução | I2: 1200 | J2: Ampliar acesso ao esporte
A3: LEG-002 | B3: Formação de Treinadoras | C3: São Paulo/SP | D3: Capacitação | E3: Federação | F3: 46266 | G3: 46568 | H3: Planejado | I3: 250 | J3: Qualificar profissionais
A4: LEG-003 | B4: Campos do Futuro | C4: Salvador/BA | D4: Infraestrutura | E4: Prefeitura | F4: 46296 | G4: 46661 | H4: Planejado | I4: 5000 | J4: Revitalizar espaços esportivos

Sheet 11_Obras
A1: ID | B1: Obra | C1: Cidade/UF | D1: Tipo | E1: Responsável | F1: Prazo | G1: % Conclusão | H1: Status | I1: Risco | J1: Observações
A2: OBR-001 | B2: Adequação de arena | C2: Rio de Janeiro/RJ | D2: Estádio | E2: Governo local | F2: 46446 | G2: 65 | H2: Em andamento | I2: Médio | J2: Exemplo
A3: OBR-002 | B3: Melhoria de acesso viário | C3: São Paulo/SP | D3: Mobilidade | E3: Prefeitura | F3: 46507 | G3: 40 | H3: Em andamento | I3: Alto | J3: Exemplo
A4: OBR-003 | B4: Centro de treinamento | C4: Recife/PE | D4: Esportivo | E4: Comitê local | F4: 46538 | G4: 20 | H4: Planejado | I4: Médio | J4: Exemplo

Sheet 12_Voluntariado
A1: Cidade | B1: Meta | C1: Inscritos | D1: Selecionados | E1: Treinados | F1: % Meta | G1: Status | H1: Responsável | I1: Observações
A2: Rio de Janeiro/RJ | B2: 1000 | C2: 0 | D2: 0 | E2: 0 | F2: =IFERROR(E2/B2,0) | G2: =IF(F2>=1,"Meta atingida",IF(F2>=0.7,"Atenção","Crítico"))
A3: São Paulo/SP | B3: 1000 | C3: 0 | D3: 0 | E3: 0 | F3: =IFERROR(E3/B3,0) | G3: =IF(F3>=1,"Meta atingida",IF(F3>=0.7,"Atenção","Crítico"))
A4: Belo Horizonte/MG | B4: 1000 | C4: 0 | D4: 0 | E4: 0 | F4: =IFERROR(E4/B4,0) | G4: =IF(F4>=1,"Meta atingida",IF(F4>=0.7,"Atenção","Crítico"))
A5: Salvador/BA | B5: 1000 | C5: 0 | D5: 0 | E5: 0 | F5: =IFERROR(E5/B5,0) | G5: =IF(F5>=1,"Meta atingida",IF(F5>=0.7,"Atenção","Crítico"))
A6: Recife/PE | B6: 1000 | C6: 0 | D6: 0 | E6: 0 | F6: =IFERROR(E6/B6,0) | G6: =IF(F6>=1,"Meta atingida",IF(F6>=0.7,"Atenção","Crítico"))
A7: Fortaleza/CE | B7: 1000 | C7: 0 | D7: 0 | E7: 0 | F7: =IFERROR(E7/B7,0) | G7: =IF(F7>=1,"Meta atingida",IF(F7>=0.7,"Atenção","Crítico"))
A8: Brasília/DF | B8: 1000 | C8: 0 | D8: 0 | E8: 0 | F8: =IFERROR(E8/B8,0) | G8: =IF(F8>=1,"Meta atingida",IF(F8>=0.7,"Atenção","Crítico"))
A9: Porto Alegre/RS | B9: 1000 | C9: 0 | D9: 0 | E9: 0 | F9: =IFERROR(E9/B9,0) | G9: =IF(F9>=1,"Meta atingida",IF(F9>=0.7,"Atenção","Crítico"))

Sheet 13_Midia
A1: Período | B1: Menções | C1: Positivas | D1: Neutras | E1: Negativas | F1: Alcance | G1: Engajamento | H1: Tema Principal | I1: Observações
A2: Jul/2026 | B2: 1250 | C2: 780 | D2: 360 | E2: 110 | F2: 2200000 | G2: 145000 | H2: Anúncio de cidades | I2: Exemplo
A3: Ago/2026 | B3: 1640 | C3: 1020 | D3: 470 | E3: 150 | F3: 3100000 | G3: 210000 | H3: Eventos preparatórios | I3: Exemplo
A4: Set/2026 | B4: 1920 | C4: 1240 | D4: 510 | E4: 170 | F4: 3800000 | G4: 290000 | H4: Patrocínios | I4: Exemplo
A5: Out/2026 | B5: 0 | C5: 0 | D5: 0 | E5: 0 | F5: 0 | G5: 0 | H5: A preencher

Sheet 14_Riscos
A1: ID | B1: Risco | C1: Área | D1: Cidade/UF | E1: Probabilidade | F1: Impacto | G1: Nível | H1: Responsável | I1: Plano de Mitigação | J1: Status
A2: RSK-001 | B2: Atraso em obra | C2: Infraestrutura | D2: São Paulo/SP | E2: Alta | F2: Alto | G2: Crítico | H2: Gestor local | I2: Plano de contingência | J2: Aberto
A3: RSK-002 | B3: Baixa adesão voluntária | C3: Voluntariado | D3: Recife/PE | E3: Média | F3: Médio | G3: Médio | H3: Coordenação | I3: Campanha de recrutamento | J3: Aberto
A4: RSK-003 | B4: Evento sem licença | C4: Operação | D4: Rio de Janeiro/RJ | E4: Baixa | F4: Alto | G4: Alto | H4: Produção | I4: Checklist legal | J4: Monitorado
A5: RSK-004 | B5: Cobertura negativa | C5: Comunicação | D5: Brasil | E5: Média | F5: Médio | G5: Médio | H5: Imprensa | I5: Plano de resposta | J5: Monitorado

Sheet 15_Config
A1: UF | B1: Região | C1: Status Evento | D1: Categoria
A2: AC | B2: Norte | C2: Planejado | D2: Fan Fest
A3: AL | B3: Nordeste | C3: Confirmado | D3: Workshop
A4: AP | B4: Norte | C4: Em execução | D4: Clínica esportiva
A5: AM | B5: Norte | C5: Realizado | D5: Seminário
A6: BA | B6: Nordeste | C6: Cancelado | D6: Ativação patrocinador
A7: CE | B7: Nordeste | D7: Legado
A8: DF | B8: Centro-Oeste | D8: Outro
A9: ES | B9: Sudeste
A10: GO | B10: Centro-Oeste
A11: MA | B11: Nordeste
A12: MT | B12: Centro-Oeste
A13: MS | B13: Centro-Oeste
A14: MG | B14: Sudeste
A15: PA | B15: Norte
A16: PB | B16: Nordeste
A17: PR | B17: Sul
A18: PE | B18: Nordeste
A19: PI | B19: Nordeste
A20: RJ | B20: Sudeste
... A28: TO | B28: Norte

Sheet 16_Manual
A1: MANUAL RÁPIDO | RADAR BRASIL 2027 V5
A4: Etapa | B4: O que fazer | C4: Aba principal | D4: Periodicidade | E4: Responsável | F4: Observação
A5: 1 | B5: Cadastrar ou atualizar eventos | C5: 02_Eventos | D5: Semanal | E5: Equipe de inteligência | F5: Preencher links e coordenadas
A6: 2 | B6: Revisar agenda futura | C6: 03_Agenda | D6: Semanal | E6: Coordenação | F6: Alimentada automaticamente
A7: 3 | B7: Atualizar indicadores IAC e INP | C7: 04_Radar_IAC / 05_Radar_INP | D7: Mensal | E7: Analistas | F7: Ajustar notas qualitativas
A8: 4 | B8: Registrar notícias e mídia | C8: 06_Noticias / 13_Midia | D8: Diária | E8: Comunicação | F8: Salvar URL da fonte
A9: 5 | B9: Atualizar obras, legado e riscos | C9: 10_Legado / 11_Obras / 14_Riscos | D9: Quinzenal | E9: PMO | F9: Priorizar itens críticos
A10: 6 | B10: Apresentar painel executivo | C10: 01_Dashboard | D10: Mensal | E10: Diretoria | F10: Atualizar arquivo antes da reunião

Sheet 17_Base_Geografica_Brasil
A1: Município | B1: UF | C1: Região | D1: Latitude | E1: Longitude | F1: Cidade-Sede | G1: Distância Estimada (km) | H1: Aeroporto Principal | I1: Potencial de Ativação | J1: Observações
A2: Rio de Janeiro | B2: RJ | C2: Sudeste | D2: -22.9068 | E2: -43.1729 | F2: Sim | G2: 0 | H2: GIG/SDU | I2: Muito Alto | J2: Cidade-sede
A3: São Paulo | B3: SP | C3: Sudeste | D3: -23.5505 | E3: -46.6333 | F3: Sim | G3: 0 | H3: GRU/CGH | I3: Muito Alto | J3: Cidade-sede
A4: Belo Horizonte | B4: MG | C4: Sudeste | D4: -19.9167 | E4: -43.9345 | F4: Sim | G4: 0 | H4: CNF | I4: Alto | J4: Cidade-sede
A5: Salvador | B5: BA | C5: Nordeste | D5: -12.9777 | E5: -38.5016 | F5: Sim | G5: 0 | H5: SSA | I5: Alto | J5: Cidade-sede
A6: Recife | B6: PE | C6: Nordeste | D6: -8.0476 | E6: -34.877 | F6: Sim | G6: 0 | H6: REC | I6: Alto | J6: Cidade-sede
A7: Fortaleza | B7: CE | C7: Nordeste | D7: -3.7319 | E7: -38.5267 | F7: Sim | G7: 0 | H7: FOR | I7: Alto | J7: Cidade-sede
A8: Brasília | B8: DF | C8: Centro-Oeste | D8: -15.7939 | E8: -47.8828 | F8: Sim | G8: 0 | H8: BSB | I8: Alto | J8: Cidade-sede
A9: Porto Alegre | B9: RS | C9: Sul | D9: -30.0346 | E9: -51.2177 | F9: Sim | G9: 0 | H9: POA | I9: Alto | J9: Cidade-sede

Sheet 18_PowerBI_Guia
A1: Guia de Integração Power BI
A3: Importe as abas de Eventos, Mapa_Base, IAC, INP e Base_Geografica.
A4: Relacione Cidade e UF.
A5: Defina Latitude e Longitude como categorias geográficas.
A6: Crie mapas, rankings e segmentações.
A7: Publique no Power BI Service.
